Workbook
Name _Toc531375826: Assumptions!$A$1
Name Hourly_Rate: 'Equipment Breakdown'!#REF!
Name Hourly_Rate: 'Saas Costs'!#REF!
Name Hourly_Rate: 'Service Costs'!#REF!
Name Hourly_Rate: 'Summation Costs'!#REF!
Name Hourly_Rate: 'Travel Costs'!#REF!
Name Hourly_Rate: #REF!
Name Parameters_AdditionalUsers: Parameters!$B$6
Name Parameters_BidirectionalInterfaceCount: Parameters!$B$41
Name Parameters_CheckRecognition_Active: Parameters!$B$13
Name Parameters_CheckRecognition_Scans: Parameters!$E$13
Name Parameters_CheckValidation_Active: Parameters!$B$14
Name Parameters_CreditIntegration_Active: Parameters!$B$22
Name Parameters_CreditIntegration_New: Parameters!$C$22
Name Parameters_Departments: Parameters!$B$7
Name Parameters_Edition: Parameters!$B$4
Name Parameters_ImageCashLetter_Active: Parameters!$B$15
Name Parameters_ImageCashLetter_New: Parameters!$C$15
Name Parameters_LengthOfProject: Parameters!$B$8
Name Parameters_NamedOrConcurrent: Parameters!$B$5
Name Parameters_OnCallSupport: Parameters!$B$10
Name Parameters_OnlineForm_Estimate: Parameters!$C$68
Name Parameters_OnlineFormCount: Parameters!$B$68
Name Parameters_OnlineFormWithWorkflow_Estimate: Parameters!$C$73
Name Parameters_OnlineFormWithWorkflowCount: Parameters!$B$73
Name Parameters_RevenueSubmission_Active: Parameters!$B$16
Name Parameters_RevenueSubmission_Submitters: Parameters!$E$16
Name Parameters_ShowPerDiemCosts: Parameters!#REF!
Name Parameters_TellerOnline_Active: Parameters!$B$18
Name Parameters_TellerOnline_Interfaces: Parameters!$D$41
Name Parameters_TellerOnline_Interfaces_New: Parameters!$E$41
Name Parameters_TellerOnline_Volume: Parameters!$E$18
Name Parameters_TravelZone: Parameters!$B$9
Name Parameters_Workflow_Active: Parameters!#REF!
Name Parameters_WorkflowSubmission_Active: Parameters!$B$17
Name Parameters_WorkflowSubmission_Workflows: Parameters!$E$17
Name SaaSUploadRate: '[1]Service Breakdown'!#REF!
Name SaaSUploadRate: 'Equipment Breakdown'!#REF!
Name SaaSUploadRate: 'Saas Costs'!#REF!
Name SaaSUploadRate: 'Service Costs'!#REF!
Name SaaSUploadRate: 'Summation Costs'!#REF!
Name SaaSUploadRate: 'Travel Costs'!#REF!
Name SaaSUploadRate: #REF!
Name Services_BiDirectionalExistingImpl: 'Variables-Services'!$D$54
Name Services_BiDirectionalExistingPlanning: 'Variables-Services'!$D$23
Name Services_BiDirectionalNewImpl: 'Variables-Services'!$D$55
Name Services_BiDirectionalNewPlanning: 'Variables-Services'!$D$24
Name Services_HourlyRate: 'Variables-Services'!$C$3
Name Services_PaymentImportExisting: 'Variables-Services'!$D$25
Name Services_PaymentImportExistingImpl: 'Variables-Services'!$D$56
Name Services_PaymentImportNew: 'Variables-Services'!$D$26
Name Services_PaymentImportNewImpl: 'Variables-Services'!$D$57
Name Software_BiDirectional: 'Variables-Software'!$C$55
Name Software_ImageCashLetter_Minimum: 'Variables-Software'!$C$19
Name Software_ImageCashLetter_PercentPricing: 'Variables-Software'!$C$18
Name Software_OnlineInterface: 'Variables-Software'!$C$56
Name Software_PaymentImport: 'Variables-Software'!$C$57
Name Trip_Day_Cost: 'Equipment Breakdown'!#REF!
Name Trip_Day_Cost: 'Saas Costs'!#REF!
Name Trip_Day_Cost: 'Service Costs'!#REF!

Sheet Parameters
A1: Category | G1: Data | H1: Notes | J1: Version | K1: 11 | L1: 45588
A2: Information
A3: Name of Agency | G3: TELLER CLIENT, STATE
A4: Teller Standard or Basic | B4: S | J4: Complexity Quotient
A5: Named or Concurrent Users | B5: N
A6: Number of Additional Users | B6: 1 | J6: Factor | K6: Computer | L6: Override
A7: Departments to Implement | B7: 2
A8: Length of Project | B8: 9 | J8: Complex Value | K8: =IF(K10<20,1,IF(K10<35, 2,3)) -> 1 | L8: =K8 -> 1
A9: Travel Zone (1-4) | B9: 2 | J9: (1=Low) (1-3)
A10: 24/7 on call support | B10: N | J10: Total | K10: =SUM(K12:K23) -> 17
A12: Applications | B12: Active | C12: New | E12: Volume | J12: Users | K12: =SUM(B6+5) -> 6
A13: Check Recognition/Bulk Scanning | B13: Y | D13: Scans: | E13: 75000 | J13: ICL | K13: =IF(B15="Y", 1, 0) -> 1
A14: Check Validation | B14: N | H14: NOTE: Requires Check Recognition | I14: =B15&C15 -> YY
A15: Image Cash Letter | B15: Y | C15: Y | G15: ???? | J15: Rev Sub | K15: =IF(B16="Y", 1, 0) -> 1
A16: Revenue Submission | B16: Y | D16: Submitters: | E16: 15
A17: Workflow Submission | B17: N | D17: Workflows: | E17: 2 | H17: NOTE: Choose Revenue or Workflow Submission | J17: Online WF | K17: =IF(B18="Y", 1, 0) -> 1
A18: Online Customer Portal | B18: Y | D18: Transactions: | E18: 50000 | G18: NOTE SCOPE | J18: Bi-Dir | K18: =+B41*2 -> 6
J19: Bi-Dir (Online) | K19: =D41 -> 0
J20: Pay Imp | K20: =B61 -> 2
A21: Integrations - Bi-Directional | B21: Active | C21: New | D21: Online | E21: Online - New | J21: Misc | K21: 0
A22: Credit Processor | B22: Y | C22: N | G22: ???? | I22: =B22&C22 -> YN
A23: Financials | B23: Y | C23: N | G23: ???? | I23: =B23&C23 -> YN
A24: Financials A/R | B24: Y | C24: N | D24: N | E24: N | G24: ???? | I24: =B24&C24 -> YN
A25: Bi-Directional - | B25: Y | C25: N | D25: N | E25: N | G25: ???? | I25: =B25&C25 -> YN
A26: Bi-Directional - | B26: Y | C26: Y | D26: N | E26: Y | G26: ???? | I26: =B26&C26 -> YY
A27: Bi-Directional - | B27: N | C27: N | D27: N | E27: N | G27: Test 3 | I27: =B27&C27 -> NN
A28: Bi-Directional - | B28: N | C28: N | D28: N | E28: N | G28: Test 4 | I28: =B28&C28 -> NN
A29: Bi-Directional - | B29: N | C29: N | D29: N | E29: N | G29: Test 5 | I29: =B29&C29 -> NN
A30: Bi-Directional - | B30: N | C30: N | D30: N | E30: N | G30: Test 6 | I30: =B30&C30 -> NN
A31: Bi-Directional - | B31: N | C31: N | D31: N | E31: N | G31: Test 7 | I31: =B31&C31 -> NN
A32: Bi-Directional - | B32: N | C32: N | D32: N | E32: N | G32: Test 8 | I32: =B32&C32 -> NN
A33: Bi-Directional - | B33: N | C33: N | D33: N | E33: N | G33: Test 9 | I33: =B33&C33 -> NN
A34: Bi-Directional - | B34: N | C34: N | D34: N | E34: N | G34: Test 10 | I34: =B34&C34 -> NN
A35: Bi-Directional - | B35: N | C35: N | D35: N | E35: N | G35: Test 11 | I35: =B35&C35 -> NN
... A39: Bi-Directional - | B39: N | C39: N | D39: N | E39: N | G39: Test 15 | I39: =B39&C39 -> NN
A41: Bi-Directional Interface Count | B41: =COUNTIF(B24:B39,"Y") -> 3 | C41: =COUNTIF(C24:C39,"Y") -> 1 | D41: =COUNTIF(D24:D39,"Y") -> 0 | E41: =COUNTIF(E24:E39,"Y") -> 1
A44: Integrations - Payment Import | B44: Active | C44: New
A45: Payment Import - | B45: Y | C45: N | G45: ???? | I45: =B45&C45 -> YN
A46: Payment Import - | B46: Y | C46: N | G46: ???? | I46: =B46&C46 -> YN
A47: Payment Import - | B47: N | C47: N | G47: Import Test 3 | I47: =B47&C47 -> NN
A48: Payment Import - | B48: N | C48: N | G48: Import Test 4 | I48: =B48&C48 -> NN
A49: Payment Import - | B49: N | C49: N | G49: Import Test 5 | I49: =B49&C49 -> NN
A50: Payment Import - | B50: N | C50: N | G50: Import Test 6 | I50: =B50&C50 -> NN
A51: Payment Import - | B51: N | C51: N | G51: Import Test 7 | I51: =B51&C51 -> NN
A52: Payment Import - | B52: N | C52: N | G52: Import Test 8 | I52: =B52&C52 -> NN
A53: Payment Import - | B53: N | C53: N | G53: Import Test 9 | I53: =B53&C53 -> NN
A54: Payment Import - | B54: N | C54: N | G54: Import Test 10 | I54: =B54&C54 -> NN
A55: Payment Import - | B55: N | C55: N | G55: Import Test 11 | I55: =B55&C55 -> NN
A56: Payment Import - | B56: N | C56: N | G56: Import Test 12 | I56: =B56&C56 -> NN
... A59: Payment Import - | B59: N | C59: N | G59: Import Test 15 | I59: =B59&C59 -> NN
A61: Payment Interface Count | B61: =COUNTIF(B45:B59,"Y") -> 2
A64: Online - Forms | B64: Count | C64: Estimate
A65: Simple | B65: 0 | C65: =B65*'Variables-Services'!D28 -> 0
A66: Medium | B66: 0 | C66: =B66*'Variables-Services'!D29 -> 0
A67: Complex | B67: 0 | C67: =B67*'Variables-Services'!D30 -> 0
A68: Form Count: | B68: =SUM(B65:B67) -> 0 | C68: =SUM(C65:C67) -> 0
A70: Simple w/ Workflow | B70: 0 | C70: =B70*'Variables-Services'!D28 + IF(B70 > 0, 'Variables-Services'!$D$31, 0) -> 0
A71: Medium w/ Workflow | B71: 0 | C71: =B71*'Variables-Services'!D29 + IF(B71 > 0, 'Variables-Services'!$D$31, 0) -> 0
A72: Complex w/ Workflow | B72: 0 | C72: =B72*'Variables-Services'!D30 + IF(B72 > 0, 'Variables-Services'!$D$31, 0) -> 0
A73: Form with Workflow Count: | B73: =SUM(B70:B72) -> 0 | C73: =SUM(C70:C72) -> 0
A75: Discount on SaaS | E75: 0
A76: Discount on Services | E76: 0
A78: Password - Price

Sheet Notes for Approver
A1: Version | B1: Version Personnel | C1: ="Version Notes for - "&Parameters!G3 -> Version Notes for - TELLER CLIENT, STATE | D1: Version Date
A3: V1 | B3: Scott
A6: V2 | B6: Josh
A8: V3 | B8: Scott
A10: V4 | B10: Josh
A12: V5 | B12: Scott

Sheet Summation Costs
A1: =Parameters!G3 -> TELLER CLIENT, STATE
A2: Investment Analysis
A4: Year | B4: Services | C4: Estimated Travel | D4: Equipment | E4: SaaS Fees | G4: Total Cost
A6: 1 | B6: =SUM('Service Costs'!$D49+'Service Costs'!$H49+'Service Costs'!$L32+'Service Costs'!$L8+'Service Costs'!$L34) -> 153180 | C6: ='Travel Costs'!$N13 -> 11370 | D6: ='Equipment Breakdown'!$F22 -> 0 | E6: ='Saas Costs'!$C60 -> 86094 | G6: =SUM(B6+C6+D6+E6) -> 250644
A7: 2 | B7: 0 | C7: 0 | D7: 0 | E7: =E6*'Variables-Software'!$C61 -> 89537.76 | G7: =SUM(B7+C7+D7+E7) -> 89537.76
A8: 3 | B8: 0 | C8: 0 | D8: 0 | E8: =E7*'Variables-Software'!$C62 -> 93119.27 | G8: =SUM(B8+C8+D8+E8) -> 93119.27
A9: 4 | B9: 0 | C9: 0 | D9: 0 | E9: =E8*'Variables-Software'!$C63 -> 96844.041 | G9: =SUM(B9+C9+D9+E9) -> 96844.041
A10: 5 | B10: 0 | C10: 0 | D10: 0 | E10: =E9*'Variables-Software'!$C64 -> 100717.8 | G10: =SUM(B10+C10+D10+E10) -> 100717.8
A11: 5 Year Cost | B11: =SUM(B6:B10) -> 153180 | C11: =SUM(C6:C10) -> 11370 | D11: =SUM(D6:D10) -> 0 | E11: =SUM(E6:E10) -> 466312.87 | G11: =SUM(G6:G10) -> 630862.87
A12: Sales Tax not included
A13: 6 | B13: 0 | C13: 0 | D13: 0 | E13: =E10*'Variables-Software'!$C65 -> 104746.51 | G13: =SUM(B13+C13+D13+E13) -> 104746.51
A14: 7 | B14: 0 | C14: 0 | D14: 0 | E14: =E13*'Variables-Software'!$C66 -> 108936.38 | G14: =SUM(B14+C14+D14+E14) -> 108936.38
A15: 8 | B15: 0 | C15: 0 | D15: 0 | E15: =E14*'Variables-Software'!$C67 -> 113293.83 | G15: =SUM(B15+C15+D15+E15) -> 113293.83
A16: 9 | B16: 0 | C16: 0 | D16: 0 | E16: =E15*'Variables-Software'!$C68 -> 117825.58 | G16: =SUM(B16+C16+D16+E16) -> 117825.58
A17: 10 | B17: 0 | C17: 0 | D17: 0 | E17: =E16*'Variables-Software'!$C69 -> 122538.61 | G17: =SUM(B17+C17+D17+E17) -> 122538.61
A18: 10 year Investment | E18: =SUM(E11:E17) -> 1033653.8 | G18: =SUM(G11:G17) -> 1198203.8
A19: Sales Tax not included
E21: =SUM(E6:E17)-E11 -> 1033653.8
A23: Service = Services+Travel Time costs

Sheet Saas Costs
A1: ="SaaS Calculations - "&Parameters!G3 -> SaaS Calculations - TELLER CLIENT, STATE
B3: Estimated Amount | C3: Pricing Amount | E3: Notes
A5: SaaS | B5: Amounts
A6: Teller Plan | B6: =IF(Parameters_Edition="S",'Variables-Software'!$C3,'Variables-Software'!C4) -> 2950 | C6: =B6 -> 2950
A7: Additional Named Users | B7: =IF(OR(Parameters_AdditionalUsers<1,Parameters_NamedOrConcurrent<>"N"),0,IF(Parameters_AdditionalUsers<45,('Variables-Software'!$C5*Parameters_AdditionalUsers),('Variables-Software'!$C6*Parameters_AdditionalUsers))) -> 60 | C7: =B7 -> 60 | E7: Base: 5
A8: Additional Concurrent Users | B8: =IF(OR(Parameters_AdditionalUsers<1,Parameters_NamedOrConcurrent="N"),0,IF(Parameters_AdditionalUsers<45,('Variables-Software'!$C5*Parameters_AdditionalUsers),('Variables-Software'!$C6*Parameters_AdditionalUsers)) * 3) -> 0 | C8: =B8 -> 0 | E8: Base: 3
C9: =B9
A10: Applications | C10: =B10
A11: =IF(Parameters_CheckRecognition_Active="Y",Parameters!A13,"") -> Check Recognition/Bulk Scanning | B11: =IF(Parameters_CheckRecognition_Active="Y",((LOOKUP(Parameters_CheckRecognition_Scans,'Variables-Software'!$B9:B16, 'Variables-Software'!$C9:C16))),0) -> 1030 | C11: =B11 -> 1030
A12: =IF(Parameters_CheckValidation_Active="Y",Parameters!A14,"") | B12: =IF(Parameters_CheckValidation_Active="Y", B11, 0) -> 0 | C12: =B12 -> 0
A13: =IF(Parameters_ImageCashLetter_Active="Y",Parameters!A15,"") -> Image Cash Letter | B13: =IF(Parameters_ImageCashLetter_Active="Y",MAX(C11 * Software_ImageCashLetter_PercentPricing, Software_ImageCashLetter_Minimum), 0) -> 669.5 | C13: =B13 -> 669.5
A14: =IF(Parameters_RevenueSubmission_Active="Y",Parameters!A16,"") -> Revenue Submission | B14: =IF(Parameters_RevenueSubmission_Active="Y",((LOOKUP(Parameters_RevenueSubmission_Submitters,'Variables-Software'!$B21:B24, 'Variables-Software'!$C21:C24))),0) -> 570 | C14: =B14 -> 570
A15: =IF(Parameters_WorkflowSubmission_Active="Y",Parameters!A17,"") | B15: =IF(Parameters_WorkflowSubmission_Active="Y",((LOOKUP(Parameters_WorkflowSubmission_Workflows,'Variables-Software'!$B26:B30, 'Variables-Software'!$C26:C30))),0) -> 0 | C15: =B15 -> 0
A16: =IF(Parameters_TellerOnline_Active="Y",Parameters!A18,"") -> Online Customer Portal | B16: =IF(Parameters_TellerOnline_Active="Y",((LOOKUP(Parameters_TellerOnline_Volume,'Variables-Software'!$B32:B44, 'Variables-Software'!$C32:C44)))+(Software_OnlineInterface*Parameters_TellerOnline_Interfaces),0) -> 700 | C16: =B16 -> 700
A17: =IF(Parameters_OnlineFormCount > 0, " Online Forms", "") | B17: =IF(Parameters_OnlineFormCount>0,LOOKUP(Parameters_OnlineFormCount,'Variables-Software'!B47:B52,'Variables-Software'!C47:C52), 0) -> 0 | C17: =B17 -> 0
A18: =IF(Parameters_OnlineFormWithWorkflowCount > 0, " Online Forms with Workflow", "") | B18: =IF(Parameters_OnlineFormWithWorkflowCount>0,LOOKUP(Parameters_OnlineFormWithWorkflowCount,'Variables-Software'!B47:B52,'Variables-Software'!C47:C52) * 2, 0) -> 0 | C18: =B18 -> 0
A20: =IF(Parameters!B24="Y", Parameters!A24&" - "&Parameters!G24, "") -> Financials A/R - ???? | B20: =IF(Parameters!B24="Y",Software_BiDirectional,0) -> 285 | C20: =B20 -> 285
A21: =IF(Parameters!B25="Y", Parameters!A25&" - "&Parameters!G25, "") -> Bi-Directional - - ???? | B21: =IF(Parameters!B25="Y",Software_BiDirectional,0) -> 285 | C21: =B21 -> 285
A22: =IF(Parameters!B26="Y", Parameters!A26&" - "&Parameters!G26, "") -> Bi-Directional - - ???? | B22: =IF(Parameters!B26="Y",Software_BiDirectional,0) -> 285 | C22: =B22 -> 285
A23: =IF(Parameters!B27="Y", Parameters!A27&" - "&Parameters!G27, "") | B23: =IF(Parameters!B27="Y",Software_BiDirectional,0) -> 0 | C23: =B23 -> 0
A24: =IF(Parameters!B28="Y", Parameters!A28&" - "&Parameters!G28, "") | B24: =IF(Parameters!B28="Y",Software_BiDirectional,0) -> 0 | C24: =B24 -> 0
A25: =IF(Parameters!B29="Y", Parameters!A29&" - "&Parameters!G29, "") | B25: =IF(Parameters!B29="Y",Software_BiDirectional,0) -> 0 | C25: =B25 -> 0
A26: =IF(Parameters!B30="Y", Parameters!A30&" - "&Parameters!G30, "") | B26: =IF(Parameters!B30="Y",Software_BiDirectional,0) -> 0 | C26: =B26 -> 0
A27: =IF(Parameters!B31="Y", Parameters!A31&" - "&Parameters!G31, "") | B27: =IF(Parameters!B31="Y",Software_BiDirectional,0) -> 0 | C27: =B27 -> 0
A28: =IF(Parameters!B32="Y", Parameters!A32&" - "&Parameters!G32, "") | B28: =IF(Parameters!B32="Y",Software_BiDirectional,0) -> 0 | C28: =B28 -> 0
A29: =IF(Parameters!B33="Y", Parameters!A33&" - "&Parameters!G33, "") | B29: =IF(Parameters!B33="Y",Software_BiDirectional,0) -> 0 | C29: =B29 -> 0
A30: =IF(Parameters!B34="Y", Parameters!A34&" - "&Parameters!G34, "") | B30: =IF(Parameters!B34="Y",Software_BiDirectional,0) -> 0 | C30: =B30 -> 0
A31: =IF(Parameters!B35="Y", Parameters!A35&" - "&Parameters!G35, "") | B31: =IF(Parameters!B35="Y",Software_BiDirectional,0) -> 0 | C31: =B31 -> 0
... A35: =IF(Parameters!B39="Y", Parameters!A39&" - "&Parameters!G39, "") | B35: =IF(Parameters!B39="Y",Software_BiDirectional,0) -> 0 | C35: =B35 -> 0
A37: =IF(Parameters!B45="Y", Parameters!A45&Parameters!G45, "") -> Payment Import - ???? | B37: =IF(Parameters!B45="Y",Software_PaymentImport,0) -> 170 | C37: =B37 -> 170
A38: =IF(Parameters!B46="Y", Parameters!A46&Parameters!G46, "") -> Payment Import - ???? | B38: =IF(Parameters!B46="Y",Software_PaymentImport,0) -> 170 | C38: =B38 -> 170
A39: =IF(Parameters!B47="Y", Parameters!A47&Parameters!G47, "") | B39: =IF(Parameters!B47="Y",Software_PaymentImport,0) -> 0 | C39: =B39 -> 0
A40: =IF(Parameters!B48="Y", Parameters!A48&Parameters!G48, "") | B40: =IF(Parameters!B48="Y",Software_PaymentImport,0) -> 0 | C40: =B40 -> 0
A41: =IF(Parameters!B49="Y", Parameters!A49&Parameters!G49, "") | B41: =IF(Parameters!B49="Y",Software_PaymentImport,0) -> 0 | C41: =B41 -> 0
A42: =IF(Parameters!B50="Y", Parameters!A50&Parameters!G50, "") | B42: =IF(Parameters!B50="Y",Software_PaymentImport,0) -> 0 | C42: =B42 -> 0
A43: =IF(Parameters!B51="Y", Parameters!A51&Parameters!G51, "") | B43: =IF(Parameters!B51="Y",Software_PaymentImport,0) -> 0 | C43: =B43 -> 0
A44: =IF(Parameters!B52="Y", Parameters!A52&Parameters!G52, "") | B44: =IF(Parameters!B52="Y",Software_PaymentImport,0) -> 0 | C44: =B44 -> 0
A45: =IF(Parameters!B53="Y", Parameters!A53&Parameters!G53, "") | B45: =IF(Parameters!B53="Y",Software_PaymentImport,0) -> 0 | C45: =B45 -> 0
A46: =IF(Parameters!B54="Y", Parameters!A54&Parameters!G54, "") | B46: =IF(Parameters!B54="Y",Software_PaymentImport,0) -> 0 | C46: =B46 -> 0
A47: =IF(Parameters!B55="Y", Parameters!A55&Parameters!G55, "") | B47: =IF(Parameters!B55="Y",Software_PaymentImport,0) -> 0 | C47: =B47 -> 0
A48: =IF(Parameters!B56="Y", Parameters!A56&Parameters!G56, "") | B48: =IF(Parameters!B56="Y",Software_PaymentImport,0) -> 0 | C48: =B48 -> 0
... A51: =IF(Parameters!B59="Y", Parameters!A59&Parameters!G59, "") | B51: =IF(Parameters!B59="Y",Software_PaymentImport,0) -> 0 | C51: =B51 -> 0
A53: =IF(Parameters_OnCallSupport="Y", Parameters!A10, "") | B53: =IF(Parameters_OnCallSupport="Y", SUM(C6:C42,C54:C57) * 0.2, 0) -> 0 | C53: =B53 -> 0
A55: Misc - 1 | B55: 0 | C55: =B55 -> 0
A56: Misc - 2 | B56: 0 | C56: =B56 -> 0
A57: Misc - 3 | B57: 0 | C57: =B57 -> 0
A58: Total: | B58: =SUM(B6:B57) -> 7174.5 | C58: =SUM(C6:C57) -> 7174.5
A59: SHI lift | B59: 0 | C59: =C58*B59 -> 0
A60: SaaS Annualized | B60: =SUM(B58*12) -> 86094 | C60: =SUM((C58+C59)*12) -> 86094

Sheet Service Costs
A1: ="Service Calculations - "&Parameters!G3 -> Service Calculations - TELLER CLIENT, STATE
B3: Estimated Hours | C3: Pricing Hours | D3: Services Costs | F3: Estimated Hours | G3: Pricing Hours | H3: Services Costs | J3: Estimated Hours | K3: Pricing Hours | L3: Standard Services Costs
A5: Service Tasks | B5: Planning | F5: Implementation | J5: Project Management | Q5: Role | R5: Hours
A6: Implementation Plan-Basic-Setup | B6: =IF(Parameters_Edition="S",'Variables-Services'!D8,'Variables-Services'!D9) -> 56 | C6: =B6 -> 56 | D6: =IF(C6>0,(C6*Services_HourlyRate),0) -> 12880 | F6: ='Variables-Services'!D36 -> 16 | G6: =F6 -> 16 | H6: =IF(G6>0,(G6*Services_HourlyRate),0) -> 3680 | J6: =SUM(Parameters!$B8*'Variables-Services'!$D69) -> 90 | K6: =J6 -> 90 | L6: =IF(K6>0,(K6*Services_HourlyRate),0) -> 20700 | Q6: Configurator Hours | R6: ='Hours By Role'!C45 -> #REF!
A7: Teller Setup | C7: =B7 -> 0 | D7: =IF(C7>0,(C7*Services_HourlyRate),0) -> 0 | F7: ='Variables-Services'!D37*Parameters_Departments -> 32 | G7: =F7 -> 32 | H7: =IF(G7>0,(G7*Services_HourlyRate),0) -> 7360 | L7: 0 | Q7: Technical Configuration Hours | R7: ='Hours By Role'!C46 -> #REF!
A8: Implementation Plan-Interfaces | J8: Total PM | L8: =L6+L7 -> 20700 | Q8: BA Hours | R8: ='Hours By Role'!C47 -> 66
A9: =IF(Parameters_ImageCashLetter_Active="Y",Parameters!A15&" - "&Parameters!G15,"""") -> Image Cash Letter - ???? | B9: =IF(Parameters_ImageCashLetter_Active="Y", 'Variables-Services'!D11,0) -> 8 | C9: =B9 -> 8 | D9: =IF(C9>0,(C9*Services_HourlyRate),0) -> 1840 | F9: =IF(Parameters!I14="NN",0,IF(Parameters!I14 ="NY",0,IF(Parameters!I14="YN", 'Variables-Services'!D39, IF(Parameters!I14="YY", 'Variables-Services'!D40,0)))) -> 12 | G9: =F9 -> 12 | H9: =IF(G9>0,(G9*Services_HourlyRate),0) -> 2760 | J9: Training | M9: Training Tasks | Q9: PM Hours | R9: ='Hours By Role'!C48 -> 63
A10: =IF(Parameters_RevenueSubmission_Active="Y", Parameters!A16, "") -> Revenue Submission | B10: =IF(Parameters_RevenueSubmission_Active="Y",((LOOKUP(Parameters_RevenueSubmission_Submitters,'Variables-Services'!$B12:B14, 'Variables-Services'!$D12:D14))),0) -> 12 | C10: =B10 -> 12 | D10: =IF(C10>0,(C10*Services_HourlyRate),0) -> 2760 | F10: =IF(Parameters_RevenueSubmission_Active="Y",((LOOKUP(Parameters_RevenueSubmission_Submitters,'Variables-Services'!$B41:B43, 'Variables-Services'!$D41:D43))),0) -> 24 | G10: =F10 -> 24 | H10: =IF(G10>0,(G10*Services_HourlyRate),0) -> 5520 | J10: =ROUNDUP(G49*'Variables-Services'!$D61,0) -> 32 | K10: =J10 -> 32 | L10: =IF(K10>0,(K10*Services_HourlyRate),0) -> 7360 | M10: UAT Support | Q10: PMA Hours | R10: ='Hours By Role'!C49 -> 27
A11: =IF(Parameters_TellerOnline_Active="Y", Parameters!A18, "") -> Online Customer Portal | B11: =IF(Parameters_TellerOnline_Active="Y",('Variables-Services'!D15+(Parameters_TellerOnline_Interfaces*'Variables-Services'!D16)),0) -> 8 | C11: =B11 -> 8 | D11: =IF(C11>0,(C11*Services_HourlyRate),0) -> 1840 | F11: =IF(Parameters_TellerOnline_Active="Y",('Variables-Services'!D44+(Parameters_TellerOnline_Interfaces*'Variables-Services'!D45)+(Parameters_TellerOnline_Interfaces_New*'Variables-Services'!D46)),0) -> 48 | G11: =F11 -> 48 | H11: =IF(G11>0,(G11*Services_HourlyRate),0) -> 11040 | J11: ='Variables-Services'!$D62*'Travel Costs'!$C9 -> 16 | K11: =J11 -> 16 | L11: =IF(K11>0,(K11*Services_HourlyRate),0) -> 3680 | M11: Prep - Training (Office) | Q11: Project Development Hours | R11: ='Hours By Role'!C50 -> 114
A12: =IF(Parameters_OnlineFormCount + Parameters_OnlineFormWithWorkflowCount > 0, " Online Forms", "") | B12: =(Parameters_OnlineForm_Estimate + Parameters_OnlineFormWithWorkflow_Estimate) * 0.2 -> 0 | C12: =B12 -> 0 | D12: =IF(C12>0,(C12*Services_HourlyRate),0) -> 0 | F12: =(Parameters_OnlineForm_Estimate + Parameters_OnlineFormWithWorkflow_Estimate) * 0.8 -> 0 | G12: =F12 -> 0 | H12: =IF(G12>0,(G12*Services_HourlyRate),0) -> 0 | J12: =IF(Parameters!K46>0, ('Variables-Services'!L13*Parameters!K46), 0) -> 0 | K12: =J12 -> 0 | L12: =IF(K12>0,(K12*'Variables-Services'!$C8),0) -> 0 | Q12: Product Development Hours | R12: ='Hours By Role'!C51 -> 0
A13: =IF(Parameters!B22="Y", Parameters!A22&" - "&Parameters!G22, "") -> Credit Processor - ???? | B13: =IF(Parameters!I22="NN",0,IF(Parameters!I22 ="NY",0,IF(Parameters!I22="YN", 'Variables-Services'!D17, IF(Parameters!I22="YY", 'Variables-Services'!D18,0)))) -> 4 | C13: =B13 -> 4 | D13: =IF(C13>0,(C13*Services_HourlyRate),0) -> 920 | F13: =IF(Parameters!I22="NN",0,IF(Parameters!I22 ="NY",0,IF(Parameters!I22="YN", 'Variables-Services'!D48, IF(Parameters!I22="YY", 'Variables-Services'!D49,0)))) -> 4 | G13: =F13 -> 4 | H13: =IF(G13>0,(G13*Services_HourlyRate),0) -> 920 | J13: 0 | K13: 0 | L13: =IF(K13>0,(K13*Services_HourlyRate),0) -> 0 | M13: Project Kickoff and Analysis | Q13: QA Hours | R13: ='Hours By Role'!C52 -> 18
A14: =IF(Parameters!B23="Y", Parameters!A23&" - "&Parameters!G23, "") -> Financials - ???? | B14: =IF(Parameters!I23="NN",0,IF(Parameters!I23 ="NY",0,IF(Parameters!I23="YN", 'Variables-Services'!D19, IF(Parameters!I23="YY", 'Variables-Services'!D20,0)))) -> 0 | C14: =B14 -> 0 | D14: =IF(C14>0,(C14*Services_HourlyRate),0) -> 0 | F14: =IF(Parameters!I23="NN",0,IF(Parameters!I23 ="NY",0,IF(Parameters!I23="YN", 'Variables-Services'!D50, IF(Parameters!I23="YY", 'Variables-Services'!D51,0)))) -> 0 | G14: =F14 -> 0 | H14: =IF(G14>0,(G14*Services_HourlyRate),0) -> 0 | J14: 0 | K14: 0 | L14: =IF(K14>0,(K14*Services_HourlyRate),0) -> 0 | M14: Interface Integration and Analysis | Q14: Trainer Hours | R14: ='Hours By Role'!C53 -> 47.6
A15: =IF(Parameters!B24="Y", Parameters!A24&" - "&Parameters!G24, "") -> Financials A/R - ???? | B15: =IF(Parameters!I24="NN",0,IF(Parameters!I24 ="NY",0,IF(Parameters!I24="YN", 'Variables-Services'!D21, IF(Parameters!I24="YY", 'Variables-Services'!D22,0)))) -> 8 | C15: =B15 -> 8 | D15: =IF(C15>0,(C15*Services_HourlyRate),0) -> 1840 | F15: =IF(Parameters!I24="NN",0,IF(Parameters!I24 ="NY",0,IF(Parameters!I24="YN", 'Variables-Services'!D52, IF(Parameters!I24="YY", 'Variables-Services'!D53,0)))) -> 20 | G15: =F15 -> 20 | H15: =IF(G15>0,(G15*Services_HourlyRate),0) -> 4600 | J15: =SUM('Travel Costs'!$C9*'Travel Costs'!$G9) -> 32 | K15: =J15 -> 32 | L15: =IF(K15>0,(K15*Services_HourlyRate),0) -> 7360 | M15: Training | Q15: Ops Hours | R15: ='Hours By Role'!C54 -> #REF!
A16: =IF(Parameters!B25="Y", Parameters!A25&Parameters!G25, "") -> Bi-Directional - ???? | B16: =IF(Parameters!I25="NN",0,IF(Parameters!I25 ="NY",0,IF(Parameters!I25="YN", Services_BiDirectionalExistingPlanning, IF(Parameters!I25="YY", Services_BiDirectionalNewPlanning,0)))) -> 8 | C16: =B16 -> 8 | D16: =IF(C16>0,(C16*Services_HourlyRate),0) -> 1840 | F16: =IF(Parameters!I25="NN",0,IF(Parameters!I25 ="NY",0,IF(Parameters!I25="YN", Services_BiDirectionalExistingImpl, IF(Parameters!I25="YY", Services_BiDirectionalNewImpl,0)))) -> 24 | G16: =F16 -> 24 | H16: =IF(G16>0,(G16*Services_HourlyRate),0) -> 5520 | J16: =SUM('Travel Costs'!$C10*'Travel Costs'!$G10) -> 16 | K16: =J16 -> 16 | L16: =IF(K16>0,(K16*Services_HourlyRate),0) -> 3680 | M16: Go Live Support | P16: Total: | R16: =SUM(R6:R15) -> #REF!
A17: =IF(Parameters!B26="Y", Parameters!A26&Parameters!G26, "") -> Bi-Directional - ???? | B17: =IF(Parameters!I26="NN",0,IF(Parameters!I26 ="NY",0,IF(Parameters!I26="YN", Services_BiDirectionalExistingPlanning, IF(Parameters!I26="YY", Services_BiDirectionalNewPlanning,0)))) -> 24 | C17: =B17 -> 24 | D17: =IF(C17>0,(C17*Services_HourlyRate),0) -> 5520 | F17: =IF(Parameters!I26="NN",0,IF(Parameters!I26 ="NY",0,IF(Parameters!I26="YN", Services_BiDirectionalExistingImpl, IF(Parameters!I26="YY", Services_BiDirectionalNewImpl,0)))) -> 100 | G17: =F17 -> 100 | H17: =IF(G17>0,(G17*Services_HourlyRate),0) -> 23000 | J17: =IF(Parameters!Q25="NN",0,IF(Parameters!Q25 ="NY",0,IF(Parameters!Q25="YN", 'Variables-Services'!L24, IF(Parameters!Q25="YY", 'Variables-Services'!#REF!,0)))) -> 0 | K17: =J17 -> 0 | L17: =IF(K17>0,(K17*Services_HourlyRate),0) -> 0
A18: =IF(Parameters!B27="Y", Parameters!A27&Parameters!G27, "") | B18: =IF(Parameters!I27="NN",0,IF(Parameters!I27 ="NY",0,IF(Parameters!I27="YN", Services_BiDirectionalExistingPlanning, IF(Parameters!I27="YY", Services_BiDirectionalNewPlanning,0)))) -> 0 | C18: =B18 -> 0 | D18: =IF(C18>0,(C18*Services_HourlyRate),0) -> 0 | F18: =IF(Parameters!I27="NN",0,IF(Parameters!I27 ="NY",0,IF(Parameters!I27="YN", Services_BiDirectionalExistingImpl, IF(Parameters!I27="YY", Services_BiDirectionalNewImpl,0)))) -> 0 | G18: =F18 -> 0 | H18: =IF(G18>0,(G18*Services_HourlyRate),0) -> 0 | J18: =IF(Parameters!P26="NN",0,IF(Parameters!P26 ="NY",0,IF(Parameters!P26="YN", 'Variables-Services'!#REF!, IF(Parameters!P26="YY", 'Variables-Services'!#REF!,0)))) -> 0 | K18: =L18/Services_HourlyRate -> 24 | L18: ='Travel Costs'!$I13 -> 5520 | M18: Travel Time
A19: =IF(Parameters!B28="Y", Parameters!A28&Parameters!G28, "") | B19: =IF(Parameters!I28="NN",0,IF(Parameters!I28 ="NY",0,IF(Parameters!I28="YN", Services_BiDirectionalExistingPlanning, IF(Parameters!I28="YY", Services_BiDirectionalNewPlanning,0)))) -> 0 | C19: =B19 -> 0 | D19: =IF(C19>0,(C19*Services_HourlyRate),0) -> 0 | F19: =IF(Parameters!I28="NN",0,IF(Parameters!I28 ="NY",0,IF(Parameters!I28="YN", Services_BiDirectionalExistingImpl, IF(Parameters!I28="YY", Services_BiDirectionalNewImpl,0)))) -> 0 | G19: =F19 -> 0 | H19: =IF(G19>0,(G19*Services_HourlyRate),0) -> 0 | J19: =IF(Parameters!P27="NN",0,IF(Parameters!P27 ="NY",0,IF(Parameters!P27="YN", 'Variables-Services'!#REF!, IF(Parameters!P27="YY", 'Variables-Services'!#REF!,0)))) -> 0 | K19: =J19 -> 0 | L19: =IF(K19>0,(K19*Services_HourlyRate),0) -> 0
A20: =IF(Parameters!B29="Y", Parameters!A29&Parameters!G29, "") | B20: =IF(Parameters!I29="NN",0,IF(Parameters!I29 ="NY",0,IF(Parameters!I29="YN", Services_BiDirectionalExistingPlanning, IF(Parameters!I29="YY", Services_BiDirectionalNewPlanning,0)))) -> 0 | C20: =B20 -> 0 | D20: =IF(C20>0,(C20*Services_HourlyRate),0) -> 0 | F20: =IF(Parameters!I29="NN",0,IF(Parameters!I29 ="NY",0,IF(Parameters!I29="YN", Services_BiDirectionalExistingImpl, IF(Parameters!I29="YY", Services_BiDirectionalNewImpl,0)))) -> 0 | G20: =F20 -> 0 | H20: =IF(G20>0,(G20*Services_HourlyRate),0) -> 0 | J20: =IF(Parameters!P28="NN",0,IF(Parameters!P28 ="NY",0,IF(Parameters!P28="YN", 'Variables-Services'!#REF!, IF(Parameters!P28="YY", 'Variables-Services'!#REF!,0)))) -> 0 | K20: =J20 -> 0 | L20: =IF(K20>0,(K20*Services_HourlyRate),0) -> 0
A21: =IF(Parameters!B30="Y", Parameters!A30&Parameters!G30, "") | B21: =IF(Parameters!I30="NN",0,IF(Parameters!I30 ="NY",0,IF(Parameters!I30="YN", Services_BiDirectionalExistingPlanning, IF(Parameters!I30="YY", Services_BiDirectionalNewPlanning,0)))) -> 0 | C21: =B21 -> 0 | D21: =IF(C21>0,(C21*Services_HourlyRate),0) -> 0 | F21: =IF(Parameters!I30="NN",0,IF(Parameters!I30 ="NY",0,IF(Parameters!I30="YN", Services_BiDirectionalExistingImpl, IF(Parameters!I30="YY", Services_BiDirectionalNewImpl,0)))) -> 0 | G21: =F21 -> 0 | H21: =IF(G21>0,(G21*Services_HourlyRate),0) -> 0 | J21: =IF(Parameters!Q43="NN",0,IF(Parameters!Q43 ="NY",0,IF(Parameters!Q43="YN", 'Variables-Services'!L25, IF(Parameters!Q43="YY", 'Variables-Services'!L26,0)))) -> 0 | K21: =J21 -> 0 | L21: =IF(K21>0,(K21*Services_HourlyRate),0) -> 0
A22: =IF(Parameters!B31="Y", Parameters!A31&Parameters!G31, "") | B22: =IF(Parameters!I31="NN",0,IF(Parameters!I31 ="NY",0,IF(Parameters!I31="YN", Services_BiDirectionalExistingPlanning, IF(Parameters!I31="YY", Services_BiDirectionalNewPlanning,0)))) -> 0 | C22: =B22 -> 0 | D22: =IF(C22>0,(C22*Services_HourlyRate),0) -> 0 | F22: =IF(Parameters!I31="NN",0,IF(Parameters!I31 ="NY",0,IF(Parameters!I31="YN", Services_BiDirectionalExistingImpl, IF(Parameters!I31="YY", Services_BiDirectionalNewImpl,0)))) -> 0 | G22: =F22 -> 0 | H22: =IF(G22>0,(G22*Services_HourlyRate),0) -> 0 | J22: =IF(Parameters!Q44="NN",0,IF(Parameters!Q44 ="NY",0,IF(Parameters!Q44="YN", 'Variables-Services'!#REF!, IF(Parameters!Q44="YY", 'Variables-Services'!#REF!,0)))) -> 0 | K22: =J22 -> 0 | L22: =IF(K22>0,(K22*Services_HourlyRate),0) -> 0
A23: =IF(Parameters!B32="Y", Parameters!A32&Parameters!G32, "") | B23: =IF(Parameters!I32="NN",0,IF(Parameters!I32 ="NY",0,IF(Parameters!I32="YN", Services_BiDirectionalExistingPlanning, IF(Parameters!I32="YY", Services_BiDirectionalNewPlanning,0)))) -> 0 | C23: =B23 -> 0 | D23: =IF(C23>0,(C23*Services_HourlyRate),0) -> 0 | F23: =IF(Parameters!I32="NN",0,IF(Parameters!I32 ="NY",0,IF(Parameters!I32="YN", Services_BiDirectionalExistingImpl, IF(Parameters!I32="YY", Services_BiDirectionalNewImpl,0)))) -> 0 | G23: =F23 -> 0 | H23: =IF(G23>0,(G23*Services_HourlyRate),0) -> 0 | J23: =IF(Parameters!Q45="NN",0,IF(Parameters!Q45 ="NY",0,IF(Parameters!Q45="YN", 'Variables-Services'!#REF!, IF(Parameters!Q45="YY", 'Variables-Services'!#REF!,0)))) -> 0 | K23: =J23 -> 0 | L23: =IF(K23>0,(K23*Services_HourlyRate),0) -> 0
A24: =IF(Parameters!B33="Y", Parameters!A33&Parameters!G33, "") | B24: =IF(Parameters!I33="NN",0,IF(Parameters!I33 ="NY",0,IF(Parameters!I33="YN", Services_BiDirectionalExistingPlanning, IF(Parameters!I33="YY", Services_BiDirectionalNewPlanning,0)))) -> 0 | C24: =B24 -> 0 | D24: =IF(C24>0,(C24*Services_HourlyRate),0) -> 0 | F24: =IF(Parameters!I33="NN",0,IF(Parameters!I33 ="NY",0,IF(Parameters!I33="YN", Services_BiDirectionalExistingImpl, IF(Parameters!I33="YY", Services_BiDirectionalNewImpl,0)))) -> 0 | G24: =F24 -> 0 | H24: =IF(G24>0,(G24*Services_HourlyRate),0) -> 0 | J24: =IF(Parameters!Q46="NN",0,IF(Parameters!Q46 ="NY",0,IF(Parameters!Q46="YN", 'Variables-Services'!#REF!, IF(Parameters!Q46="YY", 'Variables-Services'!#REF!,0)))) -> 0 | K24: =J24 -> 0 | L24: =IF(K24>0,(K24*Services_HourlyRate),0) -> 0
A25: =IF(Parameters!B34="Y", Parameters!A34&Parameters!G34, "") | B25: =IF(Parameters!I34="NN",0,IF(Parameters!I34 ="NY",0,IF(Parameters!I34="YN", Services_BiDirectionalExistingPlanning, IF(Parameters!I34="YY", Services_BiDirectionalNewPlanning,0)))) -> 0 | C25: =B25 -> 0 | D25: =IF(C25>0,(C25*Services_HourlyRate),0) -> 0 | F25: =IF(Parameters!I34="NN",0,IF(Parameters!I34 ="NY",0,IF(Parameters!I34="YN", Services_BiDirectionalExistingImpl, IF(Parameters!I34="YY", Services_BiDirectionalNewImpl,0)))) -> 0 | G25: =F25 -> 0 | H25: =IF(G25>0,(G25*Services_HourlyRate),0) -> 0 | J25: =IF(Parameters!Q47="NN",0,IF(Parameters!Q47 ="NY",0,IF(Parameters!Q47="YN", 'Variables-Services'!#REF!, IF(Parameters!Q47="YY", 'Variables-Services'!#REF!,0)))) -> 0 | K25: =J25 -> 0 | L25: =IF(K25>0,(K25*Services_HourlyRate),0) -> 0
A26: =IF(Parameters!B35="Y", Parameters!A35&Parameters!G35, "") | B26: =IF(Parameters!I35="NN",0,IF(Parameters!I35 ="NY",0,IF(Parameters!I35="YN", Services_BiDirectionalExistingPlanning, IF(Parameters!I35="YY", Services_BiDirectionalNewPlanning,0)))) -> 0 | C26: =B26 -> 0 | D26: =IF(C26>0,(C26*Services_HourlyRate),0) -> 0 | F26: =IF(Parameters!I35="NN",0,IF(Parameters!I35 ="NY",0,IF(Parameters!I35="YN", Services_BiDirectionalExistingImpl, IF(Parameters!I35="YY", Services_BiDirectionalNewImpl,0)))) -> 0 | G26: =F26 -> 0 | H26: =IF(G26>0,(G26*Services_HourlyRate),0) -> 0 | J26: =IF(Parameters!Q48="NN",0,IF(Parameters!Q48 ="NY",0,IF(Parameters!Q48="YN", 'Variables-Services'!#REF!, IF(Parameters!Q48="YY", 'Variables-Services'!#REF!,0)))) -> 0 | K26: =J26 -> 0 | L26: =IF(K26>0,(K26*Services_HourlyRate),0) -> 0
A27: =IF(Parameters!B36="Y", Parameters!A36&Parameters!G36, "") | B27: =IF(Parameters!I36="NN",0,IF(Parameters!I36 ="NY",0,IF(Parameters!I36="YN", Services_BiDirectionalExistingPlanning, IF(Parameters!I36="YY", Services_BiDirectionalNewPlanning,0)))) -> 0 | C27: =B27 -> 0 | D27: =IF(C27>0,(C27*Services_HourlyRate),0) -> 0 | F27: =IF(Parameters!I36="NN",0,IF(Parameters!I36 ="NY",0,IF(Parameters!I36="YN", Services_BiDirectionalExistingImpl, IF(Parameters!I36="YY", Services_BiDirectionalNewImpl,0)))) -> 0 | G27: =F27 -> 0 | H27: =IF(G27>0,(G27*Services_HourlyRate),0) -> 0 | J27: =IF(Parameters!Q49="NN",0,IF(Parameters!Q49 ="NY",0,IF(Parameters!Q49="YN", 'Variables-Services'!#REF!, IF(Parameters!Q49="YY", 'Variables-Services'!L33,0)))) -> 0 | K27: =J27 -> 0 | L27: =IF(K27>0,(K27*Services_HourlyRate),0) -> 0
A28: =IF(Parameters!B37="Y", Parameters!A37&Parameters!G37, "") | B28: =IF(Parameters!I37="NN",0,IF(Parameters!I37 ="NY",0,IF(Parameters!I37="YN", Services_BiDirectionalExistingPlanning, IF(Parameters!I37="YY", Services_BiDirectionalNewPlanning,0)))) -> 0 | C28: =B28 -> 0 | D28: =IF(C28>0,(C28*Services_HourlyRate),0) -> 0 | F28: =IF(Parameters!I37="NN",0,IF(Parameters!I37 ="NY",0,IF(Parameters!I37="YN", Services_BiDirectionalExistingImpl, IF(Parameters!I37="YY", Services_BiDirectionalNewImpl,0)))) -> 0 | G28: =F28 -> 0 | H28: =IF(G28>0,(G28*Services_HourlyRate),0) -> 0 | J28: =IF(Parameters!Q50="NN",0,IF(Parameters!Q50 ="NY",0,IF(Parameters!Q50="YN", 'Variables-Services'!L33, IF(Parameters!Q50="YY", 'Variables-Services'!L34,0)))) -> 0 | K28: =J28 -> 0 | L28: =IF(K28>0,(K28*Services_HourlyRate),0) -> 0
A29: =IF(Parameters!B38="Y", Parameters!A38&Parameters!G38, "") | B29: =IF(Parameters!I38="NN",0,IF(Parameters!I38 ="NY",0,IF(Parameters!I38="YN", Services_BiDirectionalExistingPlanning, IF(Parameters!I38="YY", Services_BiDirectionalNewPlanning,0)))) -> 0 | C29: =B29 -> 0 | D29: =IF(C29>0,(C29*Services_HourlyRate),0) -> 0 | F29: =IF(Parameters!I38="NN",0,IF(Parameters!I38 ="NY",0,IF(Parameters!I38="YN", Services_BiDirectionalExistingImpl, IF(Parameters!I38="YY", Services_BiDirectionalNewImpl,0)))) -> 0 | G29: =F29 -> 0 | H29: =IF(G29>0,(G29*Services_HourlyRate),0) -> 0
A30: =IF(Parameters!B39="Y", Parameters!A39&Parameters!G39, "") | B30: =IF(Parameters!I39="NN",0,IF(Parameters!I39 ="NY",0,IF(Parameters!I39="YN", Services_BiDirectionalExistingPlanning, IF(Parameters!I39="YY", Services_BiDirectionalNewPlanning,0)))) -> 0 | C30: =B30 -> 0 | D30: =IF(C30>0,(C30*Services_HourlyRate),0) -> 0 | F30: =IF(Parameters!I39="NN",0,IF(Parameters!I39 ="NY",0,IF(Parameters!I39="YN", Services_BiDirectionalExistingImpl, IF(Parameters!I39="YY", Services_BiDirectionalNewImpl,0)))) -> 0 | G30: =F30 -> 0 | H30: =IF(G30>0,(G30*Services_HourlyRate),0) -> 0
A31: =IF(Parameters!B45="Y", Parameters!A45&Parameters!G45, "") -> Payment Import - ???? | B31: =IF(Parameters!I45="NN",0,IF(Parameters!I45 ="NY",0,IF(Parameters!I45="YN", Services_PaymentImportExisting, IF(Parameters!I45="YY", Services_PaymentImportNew,0)))) -> 8 | C31: =B31 -> 8 | D31: =IF(C31>0,(C31*Services_HourlyRate),0) -> 1840 | F31: =IF(Parameters!I45="NN",0,IF(Parameters!I45 ="NY",0,IF(Parameters!I45="YN", Services_PaymentImportExistingImpl, IF(Parameters!I45="YY", Services_PaymentImportNewImpl,0)))) -> 16 | G31: =F31 -> 16 | H31: =IF(G31>0,(G31*Services_HourlyRate),0) -> 3680
A32: =IF(Parameters!B46="Y", Parameters!A46&Parameters!G46, "") -> Payment Import - ???? | B32: =IF(Parameters!I46="NN",0,IF(Parameters!I46 ="NY",0,IF(Parameters!I46="YN", Services_PaymentImportExisting, IF(Parameters!I46="YY", Services_PaymentImportNew,0)))) -> 8 | C32: =B32 -> 8 | D32: =IF(C32>0,(C32*Services_HourlyRate),0) -> 1840 | F32: =IF(Parameters!I46="NN",0,IF(Parameters!I46 ="NY",0,IF(Parameters!I46="YN", Services_PaymentImportExistingImpl, IF(Parameters!I46="YY", Services_PaymentImportNewImpl,0)))) -> 16 | G32: =F32 -> 16 | H32: =IF(G32>0,(G32*Services_HourlyRate),0) -> 3680 | J32: =SUM(J10:J29) -> 96 | K32: =SUM(K10:K29) -> 120 | L32: =SUM(L10:L29) -> 27600
A33: =IF(Parameters!B47="Y", Parameters!A47&Parameters!G47, "") | B33: =IF(Parameters!I47="NN",0,IF(Parameters!I47 ="NY",0,IF(Parameters!I47="YN", Services_PaymentImportExisting, IF(Parameters!I47="YY", Services_PaymentImportNew,0)))) -> 0 | C33: =B33 -> 0 | D33: =IF(C33>0,(C33*Services_HourlyRate),0) -> 0 | F33: =IF(Parameters!I47="NN",0,IF(Parameters!I47 ="NY",0,IF(Parameters!I47="YN", Services_PaymentImportExistingImpl, IF(Parameters!I47="YY", Services_PaymentImportNewImpl,0)))) -> 0 | G33: =F33 -> 0 | H33: =IF(G33>0,(G33*Services_HourlyRate),0) -> 0
A34: =IF(Parameters!B48="Y", Parameters!A48&Parameters!G48, "") | B34: =IF(Parameters!I48="NN",0,IF(Parameters!I48 ="NY",0,IF(Parameters!I48="YN", Services_PaymentImportExisting, IF(Parameters!I48="YY", Services_PaymentImportNew,0)))) -> 0 | C34: =B34 -> 0 | D34: =IF(C34>0,(C34*Services_HourlyRate),0) -> 0 | F34: =IF(Parameters!I48="NN",0,IF(Parameters!I48 ="NY",0,IF(Parameters!I48="YN", Services_PaymentImportExistingImpl, IF(Parameters!I48="YY", Services_PaymentImportNewImpl,0)))) -> 0 | G34: =F34 -> 0 | H34: =IF(G34>0,(G34*Services_HourlyRate),0) -> 0 | J34: SHI | K34: 0 | L34: =SUM((D49+H49+L32)*K34) -> 0
A35: =IF(Parameters!B49="Y", Parameters!A49&Parameters!G49, "") | B35: =IF(Parameters!I49="NN",0,IF(Parameters!I49 ="NY",0,IF(Parameters!I49="YN", Services_PaymentImportExisting, IF(Parameters!I49="YY", Services_PaymentImportNew,0)))) -> 0 | C35: =B35 -> 0 | D35: =IF(C35>0,(C35*Services_HourlyRate),0) -> 0 | F35: =IF(Parameters!I49="NN",0,IF(Parameters!I49 ="NY",0,IF(Parameters!I49="YN", Services_PaymentImportExistingImpl, IF(Parameters!I49="YY", Services_PaymentImportNewImpl,0)))) -> 0 | G35: =F35 -> 0 | H35: =IF(G35>0,(G35*Services_HourlyRate),0) -> 0
A36: =IF(Parameters!B50="Y", Parameters!A50&Parameters!G50, "") | B36: =IF(Parameters!I50="NN",0,IF(Parameters!I50 ="NY",0,IF(Parameters!I50="YN", Services_PaymentImportExisting, IF(Parameters!I50="YY", Services_PaymentImportNew,0)))) -> 0 | C36: =B36 -> 0 | D36: =IF(C36>0,(C36*Services_HourlyRate),0) -> 0 | F36: =IF(Parameters!I50="NN",0,IF(Parameters!I50 ="NY",0,IF(Parameters!I50="YN", Services_PaymentImportExistingImpl, IF(Parameters!I50="YY", Services_PaymentImportNewImpl,0)))) -> 0 | G36: =F36 -> 0 | H36: =IF(G36>0,(G36*Services_HourlyRate),0) -> 0
A37: =IF(Parameters!B51="Y", Parameters!A51&Parameters!G51, "") | B37: =IF(Parameters!I51="NN",0,IF(Parameters!I51 ="NY",0,IF(Parameters!I51="YN", Services_PaymentImportExisting, IF(Parameters!I51="YY", Services_PaymentImportNew,0)))) -> 0 | C37: =B37 -> 0 | D37: =IF(C37>0,(C37*Services_HourlyRate),0) -> 0 | F37: =IF(Parameters!I51="NN",0,IF(Parameters!I51 ="NY",0,IF(Parameters!I51="YN", Services_PaymentImportExistingImpl, IF(Parameters!I51="YY", Services_PaymentImportNewImpl,0)))) -> 0 | G37: =F37 -> 0 | H37: =IF(G37>0,(G37*Services_HourlyRate),0) -> 0
A38: =IF(Parameters!B52="Y", Parameters!A52&Parameters!G52, "") | B38: =IF(Parameters!I52="NN",0,IF(Parameters!I52 ="NY",0,IF(Parameters!I52="YN", Services_PaymentImportExisting, IF(Parameters!I52="YY", Services_PaymentImportNew,0)))) -> 0 | C38: =B38 -> 0 | D38: =IF(C38>0,(C38*Services_HourlyRate),0) -> 0 | F38: =IF(Parameters!I52="NN",0,IF(Parameters!I52 ="NY",0,IF(Parameters!I52="YN", Services_PaymentImportExistingImpl, IF(Parameters!I52="YY", Services_PaymentImportNewImpl,0)))) -> 0 | G38: =F38 -> 0 | H38: =IF(G38>0,(G38*Services_HourlyRate),0) -> 0
A39: =IF(Parameters!B53="Y", Parameters!A53&Parameters!G53, "") | B39: =IF(Parameters!I53="NN",0,IF(Parameters!I53 ="NY",0,IF(Parameters!I53="YN", Services_PaymentImportExisting, IF(Parameters!I53="YY", Services_PaymentImportNew,0)))) -> 0 | C39: =B39 -> 0 | D39: =IF(C39>0,(C39*Services_HourlyRate),0) -> 0 | F39: =IF(Parameters!I53="NN",0,IF(Parameters!I53 ="NY",0,IF(Parameters!I53="YN", Services_PaymentImportExistingImpl, IF(Parameters!I53="YY", Services_PaymentImportNewImpl,0)))) -> 0 | G39: =F39 -> 0 | H39: =IF(G39>0,(G39*Services_HourlyRate),0) -> 0
A40: =IF(Parameters!B54="Y", Parameters!A54&Parameters!G54, "") | B40: =IF(Parameters!I54="NN",0,IF(Parameters!I54 ="NY",0,IF(Parameters!I54="YN", Services_PaymentImportExisting, IF(Parameters!I54="YY", Services_PaymentImportNew,0)))) -> 0 | C40: =B40 -> 0 | D40: =IF(C40>0,(C40*Services_HourlyRate),0) -> 0 | F40: =IF(Parameters!I54="NN",0,IF(Parameters!I54 ="NY",0,IF(Parameters!I54="YN", Services_PaymentImportExistingImpl, IF(Parameters!I54="YY", Services_PaymentImportNewImpl,0)))) -> 0 | G40: =F40 -> 0 | H40: =IF(G40>0,(G40*Services_HourlyRate),0) -> 0
A41: =IF(Parameters!B55="Y", Parameters!A55&Parameters!G55, "") | B41: =IF(Parameters!I55="NN",0,IF(Parameters!I55 ="NY",0,IF(Parameters!I55="YN", Services_PaymentImportExisting, IF(Parameters!I55="YY", Services_PaymentImportNew,0)))) -> 0 | C41: =B41 -> 0 | D41: =IF(C41>0,(C41*Services_HourlyRate),0) -> 0 | F41: =IF(Parameters!I55="NN",0,IF(Parameters!I55 ="NY",0,IF(Parameters!I55="YN", Services_PaymentImportExistingImpl, IF(Parameters!I55="YY", Services_PaymentImportNewImpl,0)))) -> 0 | G41: =F41 -> 0 | H41: =IF(G41>0,(G41*Services_HourlyRate),0) -> 0
A42: =IF(Parameters!B56="Y", Parameters!A56&Parameters!G56, "") | B42: =IF(Parameters!I56="NN",0,IF(Parameters!I56 ="NY",0,IF(Parameters!I56="YN", Services_PaymentImportExisting, IF(Parameters!I56="YY", Services_PaymentImportNew,0)))) -> 0 | C42: =B42 -> 0 | D42: =IF(C42>0,(C42*Services_HourlyRate),0) -> 0 | F42: =IF(Parameters!I56="NN",0,IF(Parameters!I56 ="NY",0,IF(Parameters!I56="YN", Services_PaymentImportExistingImpl, IF(Parameters!I56="YY", Services_PaymentImportNewImpl,0)))) -> 0 | G42: =F42 -> 0 | H42: =IF(G42>0,(G42*Services_HourlyRate),0) -> 0
A43: =IF(Parameters!B57="Y", Parameters!A57&Parameters!G57, "") | B43: =IF(Parameters!I57="NN",0,IF(Parameters!I57 ="NY",0,IF(Parameters!I57="YN", Services_PaymentImportExisting, IF(Parameters!I57="YY", Services_PaymentImportNew,0)))) -> 0 | C43: =B43 -> 0 | D43: =IF(C43>0,(C43*Services_HourlyRate),0) -> 0 | F43: =IF(Parameters!I57="NN",0,IF(Parameters!I57 ="NY",0,IF(Parameters!I57="YN", Services_PaymentImportExistingImpl, IF(Parameters!I57="YY", Services_PaymentImportNewImpl,0)))) -> 0 | G43: =F43 -> 0 | H43: =IF(G43>0,(G43*Services_HourlyRate),0) -> 0
A44: =IF(Parameters!B58="Y", Parameters!A58&Parameters!G58, "") | B44: =IF(Parameters!I58="NN",0,IF(Parameters!I58 ="NY",0,IF(Parameters!I58="YN", Services_PaymentImportExisting, IF(Parameters!I58="YY", Services_PaymentImportNew,0)))) -> 0 | C44: =B44 -> 0 | D44: =IF(C44>0,(C44*Services_HourlyRate),0) -> 0 | F44: =IF(Parameters!I58="NN",0,IF(Parameters!I58 ="NY",0,IF(Parameters!I58="YN", Services_PaymentImportExistingImpl, IF(Parameters!I58="YY", Services_PaymentImportNewImpl,0)))) -> 0 | G44: =F44 -> 0 | H44: =IF(G44>0,(G44*Services_HourlyRate),0) -> 0
A45: =IF(Parameters!B59="Y", Parameters!A59&Parameters!G59, "") | B45: =IF(Parameters!I59="NN",0,IF(Parameters!I59 ="NY",0,IF(Parameters!I59="YN", Services_PaymentImportExisting, IF(Parameters!I59="YY", Services_PaymentImportNew,0)))) -> 0 | C45: =B45 -> 0 | D45: =IF(C45>0,(C45*Services_HourlyRate),0) -> 0 | F45: =IF(Parameters!I59="NN",0,IF(Parameters!I59 ="NY",0,IF(Parameters!I59="YN", Services_PaymentImportExistingImpl, IF(Parameters!I59="YY", Services_PaymentImportNewImpl,0)))) -> 0 | G45: =F45 -> 0 | H45: =IF(G45>0,(G45*Services_HourlyRate),0) -> 0
A46: Misc - 1 | B46: 0 | C46: =B46 -> 0 | D46: =IF(C46>0,(30*Services_HourlyRate),0) -> 0 | F46: 0 | G46: =F46 -> 0 | H46: =IF(G46>0,(G46*Services_HourlyRate),0) -> 0
A47: Misc - 2 | B47: 0 | C47: =B47 -> 0 | D47: =IF(C47>0,(C47*Services_HourlyRate),0) -> 0 | F47: 0 | G47: =F47 -> 0 | H47: =IF(G47>0,(G47*Services_HourlyRate),0) -> 0
A48: Misc - 3 | B48: 0 | C48: =B48 -> 0 | D48: =IF(C48>0,(C48*Services_HourlyRate),0) -> 0 | F48: 0 | G48: =F48 -> 0 | H48: =IF(G48>0,(G48*Services_HourlyRate),0) -> 0
A49: Total: | B49: =SUM(B6:B48) -> 144 | C49: =SUM(C6:C48) -> 144 | D49: =SUM(D6:D48) -> 33120 | F49: =SUM(F6:F48) -> 312 | G49: =SUM(G6:G48) -> 312 | H49: =SUM(H6:H48) -> 71760

Sheet Hours By Role
B5: Configuration Planning | D5: Technical Configuration Planning | F5: Interface Planning | H5: Implemenation Configuration | J5: Implemenation Technical Configuration | L5: Implementation Development | N5: Implemenation Product Work | P5: Training Preparation | R5: Training | T5: UAT/Go-Live Project | V5: UAT/Go-Live Product | X5: Project Management | Z5: Travel
A6: Implementation Plan-Basic-Setup | B6: Implementation Plan-Basic-Setup | C6: ='Service Costs'!C6 -> 56 | H6: Implementation Plan-Basic-Setup | I6: ='Service Costs'!G6 -> 16 | P6: Prep - Training (Office) | Q6: ='Service Costs'!K11 -> 16 | R6: Training | S6: ='Service Costs'!K15 -> 32 | T6: UAT Support | U6: ='Service Costs'!K10 -> 32 | X6: Project Management | Y6: ='Service Costs'!K6 -> 90 | Z6: Travel Time | AA6: ='Service Costs'!K18 -> 24
A7: Teller Setup | B7: Teller Setup | C7: ='Service Costs'!C7 -> 0 | H7: Teller Setup | I7: ='Service Costs'!G7 -> 32 | T7: Go Live Support | U7: ='Service Costs'!K16 -> 16
A8: Implementation Plan-Interfaces
A9: =IF(Parameters_CheckRecognition_Active="Y", Parameters!A13, "") -> Check Recognition/Bulk Scanning | B9: =IF(Parameters_CheckRecognition_Active="Y", Parameters!A13, "") -> Check Recognition/Bulk Scanning | C9: ='Service Costs'!#REF! -> #REF! | J9: =IF(Parameters_CheckRecognition_Active="Y", Parameters!A13, "") -> Check Recognition/Bulk Scanning
A10: =IF(Parameters_ImageCashLetter_Active="Y",Parameters!A15&" - "&Parameters!G15,"""") -> Image Cash Letter - ???? | F10: =IF(Parameters_ImageCashLetter_Active="Y",Parameters!A15&" - "&Parameters!G15,"""") -> Image Cash Letter - ???? | G10: ='Service Costs'!C9 -> 8 | J10: =IF(Parameters!I14="NN","",IF(Parameters!I14 ="NY","",IF(Parameters!I14="YN", Parameters!A15&" - "&Parameters!G15, IF(Parameters!I14="YY", "","")))) | K10: =IF(Parameters!I14="NN",0,IF(Parameters!I14 ="NY",0,IF(Parameters!I14="YN", 'Service Costs'!G9, IF(Parameters!I14="YY", 0,0)))) -> 0 | L10: =IF(Parameters!I14="NN","",IF(Parameters!I14 ="NY","",IF(Parameters!I14="YN", "", IF(Parameters!I14="YY", Parameters!A15&" - "&Parameters!G15,"")))) -> Image Cash Letter - ???? | M10: =IF(Parameters!I14="NN",0,IF(Parameters!I14 ="NY",0,IF(Parameters!I14="YN", 0, IF(Parameters!I14="YY", 'Service Costs'!G9,0)))) -> 12
A11: =IF(Parameters_RevenueSubmission_Active="Y", Parameters!A16, "") -> Revenue Submission | B11: =IF(Parameters_RevenueSubmission_Active="Y", Parameters!A16, "") -> Revenue Submission | C11: ='Service Costs'!C10 -> 12 | H11: =IF(Parameters_RevenueSubmission_Active="Y", Parameters!A16, "") -> Revenue Submission | I11: ='Service Costs'!G10 -> 24
A12: =IF(Parameters_TellerOnline_Active="Y", Parameters!A18, "") -> Online Customer Portal | B12: =IF(Parameters_TellerOnline_Active="Y", Parameters!A18, "") -> Online Customer Portal | C12: ='Service Costs'!C11 -> 8 | J12: =IF(Parameters_TellerOnline_Active="Y", Parameters!A18, "") -> Online Customer Portal | K12: ='Service Costs'!G11 -> 48
J13: =IF(Parameters!#REF!="Y", Parameters!#REF!, "") -> #REF! | K13: ='Service Costs'!#REF! -> #REF!
A14: =IF(Parameters!B22="Y", Parameters!A22&" - "&Parameters!G22, "") -> Credit Processor - ???? | F14: =IF(Parameters!B22="Y", Parameters!A22&" - "&Parameters!G22, "") -> Credit Processor - ???? | G14: ='Service Costs'!C13 -> 4 | L14: =IF(Parameters!B22="Y", Parameters!A22&" - "&Parameters!G22, "") -> Credit Processor - ???? | M14: ='Service Costs'!G13 -> 4
A15: =IF(Parameters!B23="Y", Parameters!A23&" - "&Parameters!G23, "") -> Financials - ???? | D15: =IF(Parameters!I23="NN","",IF(Parameters!I23 ="NY","",IF(Parameters!I23="YN", Parameters!A23&" - "&Parameters!G23, IF(Parameters!I23="YY", "","")))) -> Financials - ???? | E15: =IF(Parameters!I23="NN",0,IF(Parameters!I23 ="NY",0,IF(Parameters!I23="YN", 'Service Costs'!C14, IF(Parameters!I23="YY", 0,0)))) -> 0 | F15: =IF(Parameters!I23="NN","",IF(Parameters!I23 ="NY","",IF(Parameters!I23="YN", "", IF(Parameters!I23="YY", Parameters!A23&" - "&Parameters!G23,"")))) | G15: =IF(Parameters!I23="NN",0,IF(Parameters!I23 ="NY",0,IF(Parameters!I23="YN", 0, IF(Parameters!I23="YY", 'Service Costs'!C14,0)))) -> 0 | J15: =IF(Parameters!I23="NN","",IF(Parameters!I23 ="NY","",IF(Parameters!I23="YN", Parameters!A23&" - "&Parameters!G23, IF(Parameters!I23="YY", "","")))) -> Financials - ???? | K15: =IF(Parameters!I23="NN",0,IF(Parameters!I23 ="NY",0,IF(Parameters!I23="YN", 'Service Costs'!G14, IF(Parameters!I23="YY", 0,0)))) -> 0 | L15: =IF(Parameters!I23="NN","",IF(Parameters!I23 ="NY","",IF(Parameters!I23="YN", "", IF(Parameters!I23="YY", Parameters!A23&" - "&Parameters!G23,"")))) | M15: =IF(Parameters!I23="NN",0,IF(Parameters!I23 ="NY",0,IF(Parameters!I23="YN", 0, IF(Parameters!I23="YY", 'Service Costs'!G14,0)))) -> 0
A16: =IF(Parameters!B24="Y", Parameters!A24&" - "&Parameters!G24, "") -> Financials A/R - ???? | D16: =IF(Parameters!I24="NN","",IF(Parameters!I24 ="NY","",IF(Parameters!I24="YN", Parameters!A24&" - "&Parameters!G24, IF(Parameters!I24="YY", "","")))) -> Financials A/R - ???? | E16: =IF(Parameters!I24="NN",0,IF(Parameters!I24 ="NY",0,IF(Parameters!I24="YN", 'Service Costs'!C15, IF(Parameters!I24="YY", 0,0)))) -> 8 | F16: =IF(Parameters!I24="NN","",IF(Parameters!I24 ="NY","",IF(Parameters!I24="YN", "", IF(Parameters!I24="YY", Parameters!A24&" - "&Parameters!G24,"")))) | G16: =IF(Parameters!I24="NN",0,IF(Parameters!I24 ="NY",0,IF(Parameters!I24="YN", 0, IF(Parameters!I24="YY", 'Service Costs'!C15,0)))) -> 0 | J16: =IF(Parameters!I24="NN","",IF(Parameters!I24 ="NY","",IF(Parameters!I24="YN", Parameters!A24&" - "&Parameters!G24, IF(Parameters!I24="YY", "","")))) -> Financials A/R - ???? | K16: =IF(Parameters!I24="NN",0,IF(Parameters!I24 ="NY",0,IF(Parameters!I24="YN", 'Service Costs'!G15, IF(Parameters!I24="YY", 0,0)))) -> 20 | L16: =IF(Parameters!I24="NN","",IF(Parameters!I24 ="NY","",IF(Parameters!I24="YN", "", IF(Parameters!I24="YY", Parameters!A24&" - "&Parameters!G24,"")))) | M16: =IF(Parameters!I24="NN",0,IF(Parameters!I24 ="NY",0,IF(Parameters!I24="YN", 0, IF(Parameters!I24="YY", 'Service Costs'!G15,0)))) -> 0
A17: =IF(Parameters!B25="Y", Parameters!A25&Parameters!G25, "") -> Bi-Directional - ???? | F17: =IF(Parameters!B25="Y", Parameters!A25&Parameters!G25, "") -> Bi-Directional - ???? | G17: ='Service Costs'!C16 -> 8 | J17: =IF(Parameters!I25="NN","",IF(Parameters!I25 ="NY","",IF(Parameters!I25="YN", Parameters!A25&" - "&Parameters!G25, IF(Parameters!I25="YY", "","")))) -> Bi-Directional - - ???? | K17: =IF(Parameters!I25="NN",0,IF(Parameters!I25 ="NY",0,IF(Parameters!I25="YN", 'Service Costs'!G16, IF(Parameters!I25="YY", 0,0)))) -> 24 | L17: =IF(Parameters!I25="NN","",IF(Parameters!I25 ="NY","",IF(Parameters!I25="YN", "", IF(Parameters!I25="YY", Parameters!A25&" - "&Parameters!G25,"")))) | M17: =IF(Parameters!I25="NN",0,IF(Parameters!I25 ="NY",0,IF(Parameters!I25="YN", 0, IF(Parameters!I25="YY", 'Service Costs'!G16,0)))) -> 0
A18: =IF(Parameters!B26="Y", Parameters!A26&Parameters!G26, "") -> Bi-Directional - ???? | F18: =IF(Parameters!B26="Y", Parameters!A26&Parameters!G26, "") -> Bi-Directional - ???? | G18: ='Service Costs'!C17 -> 24 | J18: =IF(Parameters!I26="NN","",IF(Parameters!I26 ="NY","",IF(Parameters!I26="YN", Parameters!A26&" - "&Parameters!G26, IF(Parameters!I26="YY", "","")))) | K18: =IF(Parameters!I26="NN",0,IF(Parameters!I26 ="NY",0,IF(Parameters!I26="YN", 'Service Costs'!G17, IF(Parameters!I26="YY", 0,0)))) -> 0 | L18: =IF(Parameters!I26="NN","",IF(Parameters!I26 ="NY","",IF(Parameters!I26="YN", "", IF(Parameters!I26="YY", Parameters!A26&" - "&Parameters!G26,"")))) -> Bi-Directional - - ???? | M18: =IF(Parameters!I26="NN",0,IF(Parameters!I26 ="NY",0,IF(Parameters!I26="YN", 0, IF(Parameters!I26="YY", 'Service Costs'!G17,0)))) -> 100
A19: =IF(Parameters!B27="Y", Parameters!A27&Parameters!G27, "") | F19: =IF(Parameters!B27="Y", Parameters!A27&Parameters!G27, "") | G19: ='Service Costs'!C18 -> 0 | J19: =IF(Parameters!I27="NN","",IF(Parameters!I27 ="NY","",IF(Parameters!I27="YN", Parameters!A27&" - "&Parameters!G27, IF(Parameters!I27="YY", "","")))) | K19: =IF(Parameters!I27="NN",0,IF(Parameters!I27 ="NY",0,IF(Parameters!I27="YN", 'Service Costs'!G18, IF(Parameters!I27="YY", 0,0)))) -> 0 | L19: =IF(Parameters!I27="NN","",IF(Parameters!I27 ="NY","",IF(Parameters!I27="YN", "", IF(Parameters!I27="YY", Parameters!A27&" - "&Parameters!G27,"")))) | M19: =IF(Parameters!I27="NN",0,IF(Parameters!I27 ="NY",0,IF(Parameters!I27="YN", 0, IF(Parameters!I27="YY", 'Service Costs'!G18,0)))) -> 0
A20: =IF(Parameters!B28="Y", Parameters!A28&Parameters!G28, "") | F20: =IF(Parameters!B28="Y", Parameters!A28&Parameters!G28, "") | G20: ='Service Costs'!C19 -> 0 | J20: =IF(Parameters!I28="NN","",IF(Parameters!I28 ="NY","",IF(Parameters!I28="YN", Parameters!A28&" - "&Parameters!G28, IF(Parameters!I28="YY", "","")))) | K20: =IF(Parameters!I28="NN",0,IF(Parameters!I28 ="NY",0,IF(Parameters!I28="YN", 'Service Costs'!G19, IF(Parameters!I28="YY", 0,0)))) -> 0 | L20: =IF(Parameters!I28="NN","",IF(Parameters!I28 ="NY","",IF(Parameters!I28="YN", "", IF(Parameters!I28="YY", Parameters!A28&" - "&Parameters!G28,"")))) | M20: =IF(Parameters!I28="NN",0,IF(Parameters!I28 ="NY",0,IF(Parameters!I28="YN", 0, IF(Parameters!I28="YY", 'Service Costs'!G19,0)))) -> 0
A21: =IF(Parameters!B34="Y", Parameters!A34&Parameters!G34, "") | F21: =IF(Parameters!B34="Y", Parameters!A34&Parameters!G34, "") | G21: ='Service Costs'!C20 -> 0 | J21: =IF(Parameters!I34="NN","",IF(Parameters!I34 ="NY","",IF(Parameters!I34="YN", Parameters!A34&" - "&Parameters!G34, IF(Parameters!I34="YY", "","")))) | K21: =IF(Parameters!I34="NN",0,IF(Parameters!I34 ="NY",0,IF(Parameters!I34="YN", 'Service Costs'!G20, IF(Parameters!I34="YY", 0,0)))) -> 0 | L21: =IF(Parameters!I34="NN","",IF(Parameters!I34 ="NY","",IF(Parameters!I34="YN", "", IF(Parameters!I34="YY", Parameters!A34&" - "&Parameters!G34,"")))) | M21: =IF(Parameters!I34="NN",0,IF(Parameters!I34 ="NY",0,IF(Parameters!I34="YN", 0, IF(Parameters!I34="YY", 'Service Costs'!G20,0)))) -> 0
A22: =IF(Parameters!B45="Y", Parameters!A45&Parameters!G45, "") -> Payment Import - ???? | F22: =IF(Parameters!B45="Y", Parameters!A45&Parameters!G45, "") -> Payment Import - ???? | G22: ='Service Costs'!C31 -> 8 | J22: =IF(Parameters!B45="Y", Parameters!A45&Parameters!G45, "") -> Payment Import - ???? | K22: ='Service Costs'!G31 -> 16
A23: =IF(Parameters!B46="Y", Parameters!A46&Parameters!G46, "") -> Payment Import - ???? | F23: =IF(Parameters!B46="Y", Parameters!A46&Parameters!G46, "") -> Payment Import - ???? | G23: ='Service Costs'!C32 -> 8 | J23: =IF(Parameters!B46="Y", Parameters!A46&Parameters!G46, "") -> Payment Import - ???? | K23: ='Service Costs'!G32 -> 16
A24: =IF(Parameters!B47="Y", Parameters!A47&Parameters!G47, "") | F24: =IF(Parameters!B47="Y", Parameters!A47&Parameters!G47, "") | G24: ='Service Costs'!C33 -> 0 | J24: =IF(Parameters!B47="Y", Parameters!A47&Parameters!G47, "") | K24: ='Service Costs'!G33 -> 0
A25: =IF(Parameters!B48="Y", Parameters!A48&Parameters!G48, "") | F25: =IF(Parameters!B48="Y", Parameters!A48&Parameters!G48, "") | G25: ='Service Costs'!C34 -> 0 | J25: =IF(Parameters!B48="Y", Parameters!A48&Parameters!G48, "") | K25: ='Service Costs'!G34 -> 0
A26: =IF(Parameters!B49="Y", Parameters!A49&Parameters!G49, "") | F26: =IF(Parameters!B49="Y", Parameters!A49&Parameters!G49, "") | G26: ='Service Costs'!C35 -> 0 | J26: =IF(Parameters!B49="Y", Parameters!A49&Parameters!G49, "") | K26: ='Service Costs'!G35 -> 0
A27: =IF(Parameters!B50="Y", Parameters!A50&Parameters!G50, "") | F27: =IF(Parameters!B50="Y", Parameters!A50&Parameters!G50, "") | G27: ='Service Costs'!C36 -> 0 | J27: =IF(Parameters!B50="Y", Parameters!A50&Parameters!G50, "") | K27: ='Service Costs'!G36 -> 0
A28: =IF(Parameters!B51="Y", Parameters!A51&Parameters!G51, "") | F28: =IF(Parameters!B51="Y", Parameters!A51&Parameters!G51, "") | G28: ='Service Costs'!C37 -> 0 | J28: =IF(Parameters!B51="Y", Parameters!A51&Parameters!G51, "") | K28: ='Service Costs'!G37 -> 0
A29: =IF(Parameters!B52="Y", Parameters!A52&Parameters!G52, "") | F29: =IF(Parameters!B52="Y", Parameters!A52&Parameters!G52, "") | G29: ='Service Costs'!C38 -> 0 | J29: =IF(Parameters!B52="Y", Parameters!A52&Parameters!G52, "") | K29: ='Service Costs'!G38 -> 0
A30: ='Service Costs'!A46 -> Misc - 1 | F30: ='Service Costs'!A46 -> Misc - 1 | G30: ='Service Costs'!C46 -> 0 | L30: ='Service Costs'!A46 -> Misc - 1 | M30: ='Service Costs'!G46 -> 0
A31: ='Service Costs'!A47 -> Misc - 2 | F31: ='Service Costs'!A47 -> Misc - 2 | G31: ='Service Costs'!C47 -> 0 | L31: ='Service Costs'!A47 -> Misc - 2 | M31: ='Service Costs'!G47 -> 0
A32: ='Service Costs'!A48 -> Misc - 3 | F32: ='Service Costs'!A48 -> Misc - 3 | G32: ='Service Costs'!C48 -> 0 | L32: ='Service Costs'!A48 -> Misc - 3 | M32: ='Service Costs'!G48 -> 0
B33: Planning | H33: Implementation | P33: Training/UAT/Go-Live | X33: PM | Z33: Travel
C34: Percentage | E34: Percentage | G34: Percentage | I34: Percentage | K34: Percentage | M34: Percentage | O34: Percentage | Q34: Percentage | U34: Percentage | W34: Percentage | Y34: Percentage | AA34: Percentage
B35: Planning Configurator Percentage | C35: 0.95 | D35: Planning Technical Configurator | E35: 1 | F35: Planning BA Percentage | G35: 1 | H35: Configurator | I35: 0.9 | J35: Technical Configurator | K35: 0.9 | L35: Interface Development | M35: 0.9 | N35: Product Development | O35: 0.8 | P35: Trainer | Q35: 0.6 | R35: Trainer | S35: 1 | T35: UAT/GoLive Configurator | U35: 0.4 | V35: UAT/GoLive Product Developer | W35: 0.2 | X35: Project Manger | Y35: 0.7 | Z35: Configurator | AA35: 0.25
B36: Planning OPS Dev Environment Percentage | C36: 0.05 | H36: OPS Test and Prod Environment Percentage | I36: 0.1 | J36: OPS Test and Prod Environment Percentage | K36: 0.1 | L36: Inteface QA | M36: 0.1 | N36: Product QA | O36: 0.2 | P36: SIT QA | Q36: 0.4 | T36: UAT/GoLive Technical Configurator | U36: 0.4 | X36: Project Administrator | Y36: 0.3 | Z36: Technical Configurator | AA36: 0.25
T37: UAT/GoLive Project Developer | U37: 0.2 | Z37: BA | AA37: 0.25
Z38: Trainer | AA38: 0.25
B45: Configurator Hours | C45: {=SUM((C35*(C6:C15)),(I35*(I6:I13)),(U35*(U6:U9)),(AA35*(AA6)))} -> #REF!
B46: Technical Configuration Hours | C46: {=SUM((E35*(E6:E19)),(K35*(K6:K31)),(U36*(U6:U9)),(AA36*(AA6)))} -> #REF!
B47: BA Hours | C47: {=SUM((G35*(G6:G32)),(AA37*(AA6)))} -> 66
B48: PM Hours | C48: =SUM(Y35*Y6) -> 63
B49: PMA Hours | C49: =SUM(Y36*Y6) -> 27
B50: Project Development Hours | C50: {=SUM((M35*(M6:M31)),(U37*(U6:U9)))} -> 114
B51: Product Development Hours | C51: {=SUM((O35*(O6:O31)),(W35*(W6:W9)))} -> 0
B52: QA Hours | C52: {=SUM((M36*(M6:M31)),(Q36*(Q6:Q31)))} -> 18
B53: Trainer Hours | C53: {=SUM((Q35*(Q6:Q31)),(S35*(S6:S9)),(AA38*(AA6)))} -> 47.6
B54: Ops Hours | C54: {=SUM((C36*(C6:C31)),(K36*(K6:K31)),(I36*(I6:I31)))} -> #REF!

Sheet Travel Costs
A1: ="Travel Calculations - "&Parameters!G3 -> Travel Calculations - TELLER CLIENT, STATE
B3: Estimated hours | C3: Pricing hours | D3: Est. Number of Days | E3: Pricing Number of Days | F3: Est. Number of Staff | G3: Pricing Number of Staff | I3: Standard Travel Time | J3: Airfare | K3: Rental | L3: Per Diem Expense | M3: Est. Travel Expense | N3: Price Travel Expense
A5: Training Activity
A7: Project Kickoff and Analysis | B7: =VariablesandTravel!$C27 -> 16 | C7: =B7 -> 16 | D7: =C7/8 -> 2 | E7: =C7/8 -> 2 | F7: =VariablesandTravel!$E27 -> 2 | G7: =F7 -> 2 | I7: =VariablesandTravel!$C$5*G7 -> 1840 | J7: =VariablesandTravel!$C$15*G7 -> 1700 | K7: =IF(B7>0, (VariablesandTravel!$C$20*(E7+1)), 0) -> 375 | L7: =SUM(VariablesandTravel!$C$18, VariablesandTravel!$C$19, VariablesandTravel!$C$21) * (E7 + 1) * G7 -> 1590 | M7: =SUM(J7+K7+L7) -> 3665 | N7: =M7 -> 3665
A8: Interface Integration and Analysis | B8: =IF(Parameters_BidirectionalInterfaceCount>2, VariablesandTravel!$C31, 0) -> 16 | C8: =B8 -> 16 | D8: =C8/8 -> 2 | E8: =C8/8 -> 2 | F8: =IF(Parameters_BidirectionalInterfaceCount > 2, VariablesandTravel!$E31, 0) -> 1 | G8: =F8 -> 1 | I8: =VariablesandTravel!$C$5*G8 -> 920 | J8: =VariablesandTravel!$C$15*G8 -> 850 | K8: =IF(B8>0, (VariablesandTravel!$C$20*(E8+1)), 0) -> 375 | L8: =SUM(VariablesandTravel!$C$18, VariablesandTravel!$C$19, VariablesandTravel!$C$21) * (E8 + 1) * G8 -> 795 | M8: =SUM(J8+K8+L8) -> 2020 | N8: =M8 -> 2020
A9: Training | B9: =VariablesandTravel!$C35 -> 16 | C9: =B9 -> 16 | D9: =C9/8 -> 2 | E9: =C9/8 -> 2 | F9: =VariablesandTravel!$E35 -> 2 | G9: =F9 -> 2 | I9: =VariablesandTravel!$C$5*G9 -> 1840 | J9: =VariablesandTravel!$C$15*G9 -> 1700 | K9: =IF(B9>0, (VariablesandTravel!$C$20*(E9+1)), 0) -> 375 | L9: =SUM(VariablesandTravel!$C$18, VariablesandTravel!$C$19, VariablesandTravel!$C$21) * (E9 + 1) * G9 -> 1590 | M9: =SUM(J9+K9+L9) -> 3665 | N9: =M9 -> 3665
A10: Go Live Support | B10: =VariablesandTravel!$C39 -> 16 | C10: =B10 -> 16 | D10: =C10/8 -> 2 | E10: =D10 -> 2 | F10: =VariablesandTravel!$E39 -> 1 | G10: =F10 -> 1 | I10: =VariablesandTravel!$C$5*G10 -> 920 | J10: =VariablesandTravel!$C$15*G10 -> 850 | K10: =IF(B10>0, (VariablesandTravel!$C$20*(E10+1)), 0) -> 375 | L10: =SUM(VariablesandTravel!$C$18, VariablesandTravel!$C$19, VariablesandTravel!$C$21) * (E10 + 1) * G10 -> 795 | M10: =SUM(J10+K10+L10) -> 2020 | N10: =M10 -> 2020
A11: Other
A13: Total: | B13: =SUM(B6:B12) -> 64 | C13: =SUM(C6:C12) -> 64 | D13: =SUM(D6:D12) -> 8 | E13: =SUM(E6:E12) -> 8 | F13: =SUM(F6:F12) -> 6 | G13: =SUM(G6:G12) -> 6 | I13: =SUM(I6:I12) -> 5520 | J13: =SUM(J6:J12) -> 5100 | K13: =SUM(K6:K12) -> 1500 | L13: =SUM(L6:L12) -> 4770 | M13: =SUM(M6:M12) -> 11370 | N13: =SUM(N6:N12) -> 11370

Sheet Equipment Breakdown
A1: =Parameters!G3 -> TELLER CLIENT, STATE
A2: Equipment Calculations
A4: Item/Component | B4: Model/Description | C4: Unit Price | D4: Quantity | F4: Extended Price
A6: Receipt Printer | B6: Epson TM-M30III/USB/Thermal Printer | C6: 312 | D6: 0 | F6: =IF(D6>0,(C6*D6),0) -> 0
A7: Receipt Printer | C7: 0 | D7: 0 | F7: =IF(D7>0,(C7*D7),0) -> 0
A9: Check Scanner - single check | B9: Digital Check CheXpress CX30-IJ | C9: 523 | D9: 0 | F9: =IF(D9>0,(C9*D9),0) -> 0
A10: Check Scanner | C10: 0 | D10: 0 | F10: =IF(D10>0,(C10*D10),0) -> 0
A12: Check Scanner - bulk scanning | B12: Digital Check TS 240 | C12: 1175 | D12: 0 | F12: =IF(D12>0,(C12*D12),0) -> 0
A13: Check Scanner | C13: 0 | D13: 0 | F13: =IF(D13>0,(C13*D13),0) -> 0
A15: Cash Drawer | B15: APG Series 4000 Electronic Cash Drawer with Multi-Pro interface cable | C15: 406 | D15: 0 | F15: =IF(D15>0,(C15*D15),0) -> 0
A16: Cash Drawer | C16: 0 | D16: 0 | F16: =IF(D16>0,(C16*D16),0) -> 0
A18: Credit/Debit Device | B18: Ingenico Lane 7000 USB credit/debit PINPad with cables | C18: 786 | D18: 0 | F18: =IF(D18>0,(C18*D18),0) -> 0
A20: Cash Counter | B20: Cassida Zeus Cash Counter | C20: 2912 | D20: 0 | F20: =IF(D20>0,(C20*D20),0) -> 0
A22: Total Equipment | D22: =SUM(D6:D19) -> 0 | F22: =SUM(F6:F21) -> 0
A25: NOTE- Build in Shipping Option
A27: HONEYWELL, MS9540 VOYAGER CG KIT, SCANNER, LIGHT GRAY, USB, WITH STAND

Sheet Variables-Software
A1: ="Variables Software - "&Parameters!G3 -> Variables Software - TELLER CLIENT, STATE
A2: Software-Base | B2: Units | C2: Monthly Price | D2: Notes
A3: Teller Standard | B3: 1 | C3: 2950 | D3: Includes 5 users and is for multi-department implementations
A4: Teller Basic | B4: 1 | C4: 995 | D4: Includes 5 users
A5: Additional Users < 45 | B5: 1 | C5: 60
A6: Additional Users 45+ | B6: 1 | C6: 60 | D6: If over 50 users, check on lower per user fee
A8: Software-Applications | E8: Price per scan
A9: Check Recognition/Bulk Scanning | B9: 0 | C9: 170 | D9: Based on number of annual scans | E9: =C9/B10 -> 0.011332578
B10: 15001 | C10: 340 | E10: =C10/B11 -> 0.011332956
B11: 30001 | C11: 680 | E11: =C11/B12 -> 0.011333144
B12: 60001 | C12: 1030 | E12: =C12/B13 -> 0.010299897
B13: 100001 | C13: 1350 | E13: =C13/B14 -> 0.00899994
B14: 150001 | C14: 1600 | E14: =C14/B15 -> 0.00799996
B15: 200001 | C15: 3500 | E15: =C15/B16 -> 0.006999986
B16: 500001
A18: Image Cash Letter | B18: 1 | C18: 0.65 | D18: Percentage of check recognition costs
A19: Image Cash Letter - Minimum | C19: 170
A21: Revenue Submission | B21: 0 | C21: 450 | D21: Based on number of departments/agencies submitting
B22: 10 | C22: 570
B23: 25 | C23: 700
B24: 999 | C24: 900
A26: Workflow Submission | B26: 0 | C26: 750 | D26: Based on number of workflows
B27: 3 | C27: 850
B28: 5 | C28: 1000
B29: 10 | C29: 5000
B30: 20 | C30: 10000
E31: Cost per transaction
A32: Online Customer Portal | B32: 0 | C32: 700 | D32: Based on number of annual transactions | E32: =0.15*1.1*1.04 -> 0.1716 | F32: =E32*1.04 -> 0.178464
B33: 50001 | C33: =(B34-1)*E33/12 -> 1430 | E33: =0.15*1.1*1.04 -> 0.1716 | F33: =E33*1.04 -> 0.178464
B34: 100001 | C34: =(B35-1)*E34/12 -> 2145 | E34: =0.15*1.1*1.04 -> 0.1716 | F34: =E34*1.04 -> 0.178464
B35: 150001 | C35: =(B36-1)*E35/12 -> 2860 | E35: =0.15*1.1*1.04 -> 0.1716 | F35: =E35*1.04 -> 0.178464
B36: 200001 | C36: =(B37-1)*E36/12 -> 3575 | E36: =0.15*1.1*1.04 -> 0.1716 | F36: =E36*1.04 -> 0.178464
B37: 250001 | C37: =(B38-1)*E37/12 -> 4290 | E37: =0.15*1.1*1.04 -> 0.1716 | F37: =E37*1.04 -> 0.178464
B38: 300001 | C38: =(B39-1)*E38/12 -> 5338.6667 | E38: =0.14*1.1*1.04 -> 0.16016 | F38: =E38*1.04 -> 0.1665664
B39: 400001 | C39: =(B40-1)*E39/12 -> 6673.3333 | E39: =0.14*1.1*1.04 -> 0.16016 | F39: =E39*1.04 -> 0.1665664
B40: 500001 | C40: =(B41-1)*E40/12 -> 7436 | E40: =0.13*1.1*1.04 -> 0.14872 | F40: =E40*1.04 -> 0.1546688
B41: 600001 | C41: =(B42-1)*E41/12 -> 8675.3333 | E41: =0.13*1.1*1.04 -> 0.14872 | F41: =E41*1.04 -> 0.1546688
B42: 700001 | C42: =(B43-1)*E42/12 -> 9152 | E42: =0.12*1.1*1.04 -> 0.13728 | F42: =E42*1.04 -> 0.1427712
B43: 800001 | C43: =(B44-1)*E43/12 -> 10296 | E43: =0.12*1.1*1.04 -> 0.13728 | F43: =E43*1.04 -> 0.1427712
B44: 900001
A46: Online Forms | B46: 0 | D46: Based on number of forms
B47: 1 | C47: 50
B48: 2 | C48: 100
B49: 5 | C49: 200
B50: 10 | C50: 300
B51: 15 | C51: 400
B52: 25 | C52: 500
A54: Software-Integrations
A55: Monthly cost for Real-time interface | B55: 1 | C55: 285
A56: Monthly per online interface fee | B56: 1 | C56: 170
A57: Monthly cost for Payment Import interface | B57: 1 | C57: 170
A58: Financial Interface | B58: 1 | C58: 0
A60: Software-Inflation
A61: Year 2 | B61: 1 | C61: 1.04
A62: Year 3 | B62: 1 | C62: 1.04
A63: Year 4 | B63: 1 | C63: 1.04
A64: Year 5 | B64: 1 | C64: 1.04
A65: Year 6 | B65: 1 | C65: 1.04
A66: Year 7 | B66: 1 | C66: 1.04
A67: Year 8 | B67: 1 | C67: 1.04
A68: Year 9 | B68: 1 | C68: 1.04
A69: Year 10 | B69: 1 | C69: 1.04

Sheet Variables-Services
A1: ="Variables Services - "&Parameters!G3 -> Variables Services - TELLER CLIENT, STATE
A2: Services Cost | B2: Units | C2: Monthly Price | D2: Hours | E2: Notes
A3: Hourly Rate | C3: 230
A4: Project Management Hourly Rate | C4: 230
A7: Planning
A8: Implementation Plan - Standard | D8: 56
A9: Implementation Plan - Basic | D9: =D8/2 -> 28
A10: =IF(Parameters_CheckRecognition_Active="Y", Parameters!A13, "") -> Check Recognition/Bulk Scanning | D10: 0 | E10: Future
A11: =IF(Parameters_ImageCashLetter_Active="Y", Parameters!A15, "") -> Image Cash Letter | D11: 8
A12: =IF(Parameters_RevenueSubmission_Active="Y", Parameters!A16, "") -> Revenue Submission | B12: 0 | D12: 8
B13: 10 | D13: 12
B14: 25 | D14: 16
A15: =IF(Parameters_TellerOnline_Active="Y", Parameters!A18&" - Base", "") -> Online Customer Portal - Base | D15: 8
A16: =IF(Parameters_TellerOnline_Active="Y", Parameters!A18&" - Per Integration", "") -> Online Customer Portal - Per Integration | D16: 4
A17: =IF(Parameters!B22="Y", Parameters!A22&" - Existing", "") -> Credit Processor - Existing | D17: 4
A18: =IF(Parameters!B22="Y", Parameters!A22&" - New", "") -> Credit Processor - New | D18: 16
A19: =IF(Parameters!B23="Y", Parameters!A23&" - Existing", "") -> Financials - Existing | D19: 0
A20: =IF(Parameters!B23="Y", Parameters!A23&" - New", "") -> Financials - New | D20: 0
A21: =IF(Parameters!B24="Y", Parameters!A24&" - Existing", "") -> Financials A/R - Existing | D21: 8
A22: =IF(Parameters!B24="Y", Parameters!A24&" - New", "") -> Financials A/R - New | D22: 16
A23: =IF(Parameters!B25="Y", Parameters!A25& "- Existing", "") -> Bi-Directional - - Existing | D23: 8 | E23: NOTE: if we know this is an older product consider extra hours
A24: =IF(Parameters!B25="Y", Parameters!A25&" - New", "") -> Bi-Directional - - New | D24: 24
A25: =IF(Parameters!B45="Y", Parameters!A45&" - Existing", "") -> Payment Import - - Existing | D25: 8
A26: =IF(Parameters!B45="Y", Parameters!A45&" - New", "") -> Payment Import - - New | D26: 8
A28: Online Form - Simple | D28: 20
A29: Online Form - Medium | D29: 40
A30: Online Form - Complex | D30: 60
A31: Online Form - Workflow | D31: 50
A34: Implementation
A36: Implementation Plan - Setup | D36: 16
A37: Teller Config per Department | D37: 16
A38: Check Recognition/Bulk Scanning | D38: 0 | E38: Future
A39: Image Cash Letter - Existing | D39: 8
A40: Image Cash Letter - New | D40: 12
A41: Revenue Submission | B41: 0 | D41: 16
B42: 10 | D42: 24
B43: 25 | D43: 32
A44: Online Customer Portal - New Portal | D44: 32
A45: Online Customer Portal - Existing Interface (Base) | D45: 8
A46: Online Customer Portal - New Interface (Additional) | D46: 16
A48: Credit Processor - Existing | D48: 4
A49: Credit Processor - New | D49: 80
A50: Financials - Existing | D50: 0
A51: Financials - New | D51: 0
A52: Financials A/R - Existing | D52: 20
A53: Financials A/R - New | D53: 64
A54: Bi-Directional - - Existing | D54: 24 | E54: NOTE: if we know this is an older product consider extra hours
A55: Bi-Directional - - New | D55: 100
A56: Payment Import - - Existing | D56: 16
A57: Payment Import - - New | D57: 16
A59: Training
A61: UAT Preparation | D61: 0.1 | E61: Percentage of Implementation Hours
A62: Training Preparation | D62: 1 | E62: Factor of number of training days
D63: 0
D64: 0
D65: 0
D66: 0
A68: Project Management
A69: Hours per month | D69: 10

Sheet VariablesandTravel
A1: ="Variables Services/Travel - "&Parameters!G3 -> Variables Services/Travel - TELLER CLIENT, STATE
A2: Services Cost | B2: Units | C2: Monthly Price | E2: Hours | F2: Notes
A3: Hourly Rate | B3: 1 | C3: ='Variables-Services'!$C3 -> 230
A4: Project Management Hourly Rate | B4: 1 | C4: ='Variables-Services'!$C3 -> 230
A5: Travel Time Costs | B5: 1 | C5: =E5*C3 -> 920 | E5: 4
B6: 1
B7: 1
A9: Travel Factors
A10: Travel Trip Cost | F10: Flight/Drive
A11: Travel Trip Cost - Zone 1 | B11: 1 | C11: 750 | F11: Zone: Western US
A12: Travel Trip Cost - Zone 2 | B12: 2 | C12: 850 | F12: Zone: Mid-Western US
A13: Travel Trip Cost - Zone 3 | B13: 3 | C13: 950 | F13: Zone: Eastern US
A14: Travel Trip Cost - Zone 4 | B14: 4 | C14: 1050 | F14: Outside Continental US or Other
A15: Actual Zone (From Parameters) | B15: =Parameters!B9 -> 2 | C15: =IF(B15=1,C11,IF(B15=2,C12,IF(B15=3,C13,IF(B15=4,C14,0)))) -> 850
A17: Per Diem Expense
A18: - Per Diem Hotels | B18: 1 | C18: 180
A19: - Per Diem Meals | B19: 1 | C19: 60
A20: - Per Diem Rental | B20: 1 | C20: 125
A21: - Per Diem Other | B21: 1 | C21: 25
A23: Travel Trips | B23: Complex Factor | C23: Hours | D23: Days | E23: People | F23: Notes
A24: Kickoff Analysis | B24: 1 | C24: 16 | D24: =C24/8 -> 2 | E24: 2
B25: 2 | C25: 24 | D25: =C25/8 -> 3 | E25: 2
B26: 3 | C26: 32 | D26: =C26/8 -> 4 | E26: 2
A27: Actual (From Parameters) | B27: =Parameters!$L8 -> 1 | C27: =IF($B$27=1,C24,IF($B$27=2,C25,IF($B$27=3,C26,0))) -> 16 | D27: =IF($B$27=1,D24,IF($B$27=2,D25,IF($B$27=3,D26,0))) -> 2 | E27: =IF($B$27=1,E24,IF($B$27=2,E25,IF($B$27=3,E26,0))) -> 2
A28: Interface Integration and Analysis | B28: 1 | C28: 16 | D28: =C28/8 -> 2 | E28: 1
B29: 2 | C29: 16 | D29: =C29/8 -> 2 | E29: 2
B30: 3 | C30: 16 | D30: 3 | E30: 2
A31: Actual (From Parameters) | B31: =Parameters!$L8 -> 1 | C31: =IF($B$27=1,C28,IF($B$27=2,C29,IF($B$27=3,C30,0))) -> 16 | D31: =IF($B$27=1,D28,IF($B$27=2,D29,IF($B$27=3,D30,0))) -> 2 | E31: =IF($B$27=1,E28,IF($B$27=2,E29,IF($B$27=3,E30,0))) -> 1
A32: On Site Setup and Pre-UAT | B32: 1 | C32: 16 | D32: =C32/8 -> 2 | E32: 2
B33: 2 | C33: 24 | D33: =C33/8 -> 3 | E33: 2
B34: 3 | C34: 32 | D34: =C34/8 -> 4 | E34: 2
A35: Actual (From Parameters) | B35: =Parameters!$L8 -> 1 | C35: =IF($B$27=1,C32,IF($B$27=2,C33,IF($B$27=3,C34,0))) -> 16 | D35: =IF($B$27=1,D32,IF($B$27=2,D33,IF($B$27=3,D34,0))) -> 2 | E35: =IF($B$27=1,E32,IF($B$27=2,E33,IF($B$27=3,E34,0))) -> 2
A36: Go Live Support | B36: 1 | C36: 16 | D36: =C36/8 -> 2 | E36: 1
B37: 2 | C37: 16 | D37: =C37/8 -> 2 | E37: 1
B38: 3 | C38: 24 | D38: =C38/8 -> 3 | E38: 1
A39: Actual (From Parameters) | B39: =Parameters!$L8 -> 1 | C39: =IF($B$27=1,C36,IF($B$27=2,C37,IF($B$27=3,C38,0))) -> 16 | D39: =IF($B$27=1,D36,IF($B$27=2,D37,IF($B$27=3,D38,0))) -> 2 | E39: =IF($B$27=1,E36,IF($B$27=2,E37,IF($B$27=3,E38,0))) -> 1
A41: Implementation Plan - per Real-Time interface | B41: 1 | C41: =A25
A42: Total Per Diem | B42: 1 | C42: =SUM(C18:C22) -> 390 | D42: =SUM(D18:D22) -> 0 | E42: =SUM(E18:E22) -> 0
A43: Kickoff Analysis | B43: 1 | C43: 180 | D43: 180 | E43: 180
A44: Project Management Hourly Rate | B44: 1 | C44: 180 | D44: 180 | E44: 180
A45: Travel Time Costs | B45: 1 | C45: 600 | D45: 600 | E45: 600
A46: Implementation Plan - per Real-Time interface | B46: 1
A47: Total Per Diem | B47: 1 | C47: =SUM(C23:C41) -> 312 | D47: =SUM(D23:D41) -> 40 | E47: =SUM(E23:E41) -> 26

Sheet Variables-Optional
A1: ="Variables Optional - "&Parameters!G3 -> Variables Optional - TELLER CLIENT, STATE
A4: Reserved future use
A5: - Process consulting, etc.

Sheet Assumptions
A1: Assumptions | B1: Notes
A2: Pricing is based on:
A3: =+(5+Parameters!$E6)&" users, including peripheral hardware. More or less users might be required as will be determined during discovery and analysis sessions." -> 5 users, including peripheral hardware. More or less users might be required as will be determined during discovery and analysis sessions.
A4: =IF(Parameters_CheckRecognition_Active="Y", "Check Recognition/Scanning for up to annual scan volume of ","")&Parameters!E13 -> Check Recognition/Scanning for up to annual scan volume of 75000
A5: =IF(Parameters_ImageCashLetter_Active="Y", "Image Cash Letter (ICL) with - ","")&Parameters!G15 -> Image Cash Letter (ICL) with - ????
A6: =IF(Parameters_RevenueSubmission_Active="Y", "Revenue Submission for following number of departments/agencies - ","")&Parameters!E16 -> Revenue Submission for following number of departments/agencies - 15
A7: =IF(Parameters_TellerOnline_Active="Y", "Online Customer Portal for an application total equal - ","")&Parameters!E18 -> Online Customer Portal for an application total equal - 50000
A8: =IF(Parameters!#REF!="Y", "Online Workflow Document application total equal - ","")&Parameters!#REF! -> #REF!
A9: Integrations - Real Time
A10: =IF(Parameters!B22="Y", "Credit Processor - ","")&Parameters!G22 -> Credit Processor - ????
A11: =IF(Parameters!B23="Y", "Integration with Financial - ","")&Parameters!G23 -> Integration with Financial - ????
A12: =IF(Parameters!B24="Y", "Integration with Financial A/R - ","")&Parameters!G24 -> Integration with Financial A/R - ????
A13: =IF(Parameters!B25="Y", "Integration with - ","")&Parameters!G25 -> Integration with - ????
A14: =IF(Parameters!B26="Y", "Integration with - ","")&Parameters!G26 -> Integration with - ????
A15: =IF(Parameters!B27="Y", "Integration with - ","")&Parameters!G27 -> Test 3
A16: =IF(Parameters!B28="Y", "Integration with - ","")&Parameters!G28 -> Test 4
A17: =IF(Parameters!B34="Y", "Integration with - ","")&Parameters!G34 -> Test 10
A19: Integrations - Real Time
A20: o Integration with Workday Financials and Accounts Receivables
A21: o Image Cash Letter to Wells Fargo
A22: o Check Recognition/Scanning (up to 15,000 annual scans).
A23: o Online Customer Portal for Workday A/R (up to 50,000 annual transactions)
A24: o Integration with Wells Fargo as the Credit Processor.
A25: o Selected POS equipment (5 Digital Check CheXpress CX30 scanners).
A26: o Revenue Submission Module
A27: o Fees could increase or decrease depending on the detailed needs of the Client and a complete discovery by Can/Am.
A28: · All quoted pricing is in US dollars and exclusive of any applicable taxes.
A29: · All deliverables are provided on a Fixed Price basis.
A30: · First year of hosting/licensing will be billed upon contract signing.
... A46: · For all business application interfaces, obtain and provide the Teller implementation team with all API specifications and/or database connections and/or example files as well as a dev/test environment suitable for development of the interfaces. Where a test environment is not available, Client will provide a technical resource that will provide sample input data and validation of all output batch files.
